Workbook

Sheet Graphique
C5: Code Minier_2003 | D5: Code Minier_2015 | E5: Droit Commun | F5: Guinée 2011
B6: Etat | C6: 0.49379191 | D6: 0.60766343 | E6: 0.67665692 | F6: 0.66462504
B7: Endeavour Mining | C7: 0.50620809 | D7: 0.39233657 | E7: 0.32334308 | F7: 0.33537496
B17: Année | C17: 2011 | D17: 2012 | E17: 2013 | F17: 2014 | G17: 2015 | H17: 2016 | I17: 2017 | J17: 2018 | K17: 2019 | L17: 2020 | M17: 2021
B18: Cash flow avant impôt | C18: =C20/1000 -> -73445.792 | D18: =D20/1000 -> -241407.82 | E18: =E20/1000 -> 116802.04 | F18: =F20/1000 -> 141544.2 | G18: =G20/1000 -> 93764.638 | H18: =H20/1000 -> 55567.633 | I18: =I20/1000 -> 110004.64 | J18: =J20/1000 -> 77958.596 | ... M18: =M20/1000 -> 141930.05
B19: Cash flow après impôt | C19: =C21/1000 -> -73808.871 | D19: =D21/1000 -> -241760.75 | E19: =E21/1000 -> 90770.113 | F19: =F21/1000 -> 103094.14 | G19: =G21/1000 -> 71085.597 | H19: =H21/1000 -> 43835.694 | I19: =I21/1000 -> 75540.704 | J19: =J21/1000 -> 54117.593 | ... M19: =M21/1000 -> 98672.88
B20: Cash flow avant impôt | C20: -73445792 | D20: -241407817 | E20: 116802045 | F20: 141544202 | G20: 93764638 | H20: 55567633 | I20: 110004643 | J20: 77958596 | K20: 63568427 | L20: 97578084 | M20: 141930048
B21: Cash flow après impôt | C21: -73808871 | D21: -2.4176075e+08 | E21: 90770113 | F21: 1.0309414e+08 | G21: 71085597 | H21: 43835694 | I21: 75540704 | J21: 54117593 | K21: 45531853 | L21: 68247922 | M21: 98672880
B29: Composition du TEMI
C30: Composition du TEMI | D30: Montant total
B31: Redevance superficiaire | C31: =D31/D37 -> 0.0087984768 | D31: =SUM('Modèle de base (CM 2003)'!C33:M33) -> 4823469.2
B32: Droits fixes | C32: =D32/D37 -> 1.8499741e-05 | D32: ='Modèle de base (CM 2003)'!C29 -> 10141.861
B33: Impôts sur les sociétés (IS/IMF) | C33: =D33/D37 -> 0.62780272 | D33: =SUM('Modèle de base (CM 2003)'!C44:M44) -> 3.4417175e+08
B34: Redevance proportionnelle | C34: =D34/D37 -> 0.18120541 | D34: =SUM('Modèle de base (CM 2003)'!C37:M37) -> 99339776
B35: Dividende de l'Etat | C35: =D35/D37 -> 0.11659193 | D35: =SUM('Modèle de base (CM 2003)'!C48:M48) -> 63917610
B36: Impôt sur les dividendes | C36: =D36/D37 -> 0.065582963 | D36: =SUM('Modèle de base (CM 2003)'!C50:M50) -> 35953656
B37: Recettes totales de l'Etat | C37: =SUM(C31:C36) -> 1 | D37: =SUM(D31:D36) -> 5.482164e+08
B43: Prix de l'or | C43: 1100 | D43: 1300 | E43: 1600
B44: TEMI_CM 2003 | C44: =Récapitulatif!C23 -> 0.81343486 | D44: =Récapitulatif!D23 -> 0.49379191 | E44: =Récapitulatif!E23 -> 0.41493617
B47: Prix de l'or | C47: 1100 | D47: 1300 | E47: 1600
B48: TEMI_CM 2015 | C48: =Récapitulatif!C36 -> 0.98881004 | D48: =Récapitulatif!D36 -> 0.60766343 | E48: =Récapitulatif!E36 -> 0.51578801
C61: Flux net de trésorerie avant impôt | D61: ='Modèle de base (CM 2003)'!C25 -> -73445792 | E61: ='Modèle de base (CM 2003)'!D25 -> -241407817 | F61: ='Modèle de base (CM 2003)'!E25 -> 174154845 | G61: ='Modèle de base (CM 2003)'!F25 -> 206115602 | H61: ='Modèle de base (CM 2003)'!G25 -> 150706738 | I61: ='Modèle de base (CM 2003)'!H25 -> 106065133 | J61: ='Modèle de base (CM 2003)'!I25 -> 173295943 | K61: ='Modèle de base (CM 2003)'!J25 -> 128268596 | ... N61: ='Modèle de base (CM 2003)'!M25 -> 177741048
C62: Revenu de l'Etat | D62: ='Modèle de base (CM 2003)'!C53 -> 363078.64 | E62: ='Modèle de base (CM 2003)'!D53 -> 352936.77 | F62: ='Modèle de base (CM 2003)'!E53 -> 60834890 | G62: ='Modèle de base (CM 2003)'!F53 -> 82096586 | H62: ='Modèle de base (CM 2003)'!G53 -> 55693081 | I62: ='Modèle de base (CM 2003)'!H53 -> 36861266 | J62: ='Modèle de base (CM 2003)'!I53 -> 75618286 | K62: ='Modèle de base (CM 2003)'!J53 -> 54780665 | ... N62: ='Modèle de base (CM 2003)'!M53 -> 77871841
C63: Profit de l'investisseur | F63: ='Modèle de base (CM 2003)'!E49 -> 62503669 | G63: ='Modèle de base (CM 2003)'!F49 -> 88053202 | H63: ='Modèle de base (CM 2003)'!G49 -> 55955953 | I63: ='Modèle de base (CM 2003)'!H49 -> 33188013 | J63: ='Modèle de base (CM 2003)'!I49 -> 79861929 | K63: ='Modèle de base (CM 2003)'!J49 -> 56454445 | L63: ='Modèle de base (CM 2003)'!K49 -> 43168178 | M63: ='Modèle de base (CM 2003)'!L49 -> 66001674 | N63: ='Modèle de base (CM 2003)'!M49 -> 90071426
C64: Investissement | D64: ='Modèle de base (CM 2003)'!C23*(-1) -> -73445792 | E64: ='Modèle de base (CM 2003)'!D23*(-1) -> -241407817
C65: Coût de production | F65: ='Modèle de base (CM 2003)'!E23 -> 131726755 | G65: ='Modèle de base (CM 2003)'!F23 -> 138265198 | H65: ='Modèle de base (CM 2003)'!G23 -> 152984462 | I65: ='Modèle de base (CM 2003)'!H23 -> 163254867 | J65: ='Modèle de base (CM 2003)'!I23 -> 164257657 | K65: ='Modèle de base (CM 2003)'!J23 -> 140051404 | L65: ='Modèle de base (CM 2003)'!K23 -> 114270273 | M65: ='Modèle de base (CM 2003)'!L23 -> 101059316 | N65: ='Modèle de base (CM 2003)'!M23 -> 13250952
C66: Coût de rehabilitation
B86: Recettes totales | D86: =SUM('Code Minier 2015'!C54:M54) -> 3.0613969e+08
B87: Redevance proportionnelles | D87: =SUM('Code Minier 2015'!C37:M37) -> 80713568
B88: Fonds de développement local (1%) | D88: =SUM('Code Minier 2015'!E40:M40) -> 20178392
B89: Fonds de développement local total | C89: =D89/D86 -> 0.11864226 | D89: =D88+(D87*20%) -> 36321106
B90: Etat central | C90: =D90/D86 -> 0.88135774 | D90: =D86-D89 -> 2.6981858e+08
C104: Tri avant impôt | D104: ='Modèle de base (CM 2003)'!E27 -> -0.3913088 | E104: ='Modèle de base (CM 2003)'!F27 -> 0.11243079 | F104: ='Modèle de base (CM 2003)'!G27 -> 0.2768997 | G104: ='Modèle de base (CM 2003)'!H27 -> 0.3407976 | H104: ='Modèle de base (CM 2003)'!I27 -> 0.40012659 | I104: ='Modèle de base (CM 2003)'!J27 -> 0.42540794 | J104: ='Modèle de base (CM 2003)'!K27 -> 0.43824983 | K104: ='Modèle de base (CM 2003)'!L27 -> 0.44942432 | L104: ='Modèle de base (CM 2003)'!M27 -> 0.45818507
C105: Tri après impôt_CM 2003 | E105: ='Modèle de base (CM 2003)'!F57 -> -0.1492555 | F105: ='Modèle de base (CM 2003)'!G57 -> 0.024126629 | G105: ='Modèle de base (CM 2003)'!H57 -> 0.10169092 | H105: ='Modèle de base (CM 2003)'!I57 -> 0.17018122 | I105: ='Modèle de base (CM 2003)'!J57 -> 0.20296263 | J105: ='Modèle de base (CM 2003)'!K57 -> 0.2221153 | K105: ='Modèle de base (CM 2003)'!L57 -> 0.23986363 | L105: ='Modèle de base (CM 2003)'!M57 -> 0.2547242
C106: Tri après impôt_CM 2015 | E106: ='Code Minier 2015'!F58 -> -0.274356 | F106: ='Code Minier 2015'!G58 -> -0.1096526 | G106: ='Code Minier 2015'!H58 -> -0.037981949 | H106: ='Code Minier 2015'!I58 -> 0.039866811 | I106: ='Code Minier 2015'!J58 -> 0.077305814 | J106: ='Code Minier 2015'!K58 -> 0.10075814 | K106: ='Code Minier 2015'!L58 -> 0.12587439 | L106: ='Code Minier 2015'!M58 -> 0.15060915
C117: Cours de l'Or | D117: 1100 | E117: 1300 | F117: 1600
C118: TEMI | D118: 1.0867363 | E118: 0.60766343 | F118: 0.49941613
C119: TRI | D119: 0.13994104 | E119: 0.27738179 | F119: 0.45818507

Sheet Récapitulatif
B1: Code minier de 2003 | D1: Code minier de 2015
B2: Phase préparatoire | C2: Phase de production | D2: Phase préparatoire | E2: Phase de production | I2: Mine | J2: HOUNDE
A3: Durée du titre | B3: 20 ans | D3: idem | I3: Investisseur | J3: ENDEAVOUR MINING
A4: Renouvellement | B4: 5 ans | D4: idem | I4: Date d'octroi du permis d'exploitation | J4: 42040
A5: Part de l'Etat | B5: 0.1 | D5: idem | I5: Date de signature de la convention | J5: 42338
A6: Redevances fixes | B6: 5 millions de FCFA | C6: 0 | D6: idem | E6: idem | I6: Début probable de la production | J6: 21 mois la signature de la convention
A7: Redevances superficiaires | B7: 0 | C7: 7,5 millions années 1 à 5; 10 millions années 6 à 10 et 15 millions après | D7: idem | E7: idem | I7: Durée d'exploitation | J7: 11 ans
A8: Redevances proportionnelles | B8: 0 | D8: idem | E8: idem | I8: Superficie de la mine | J8: 23,2 km2
A9: Fonds de développement local | E9: Investisseur 1% du chiffres d'affaires | I9: Teneur moyenne en g/t | J9: 1.97
A10: Réhabilitation | B10: Investisseur | D10: Idem | I10: Produtction en koz | J10: 172464.89
A11: Impot sur les sociétés | B11: Exonération | C11: Taux de droit commun réduit de 10 points | D11: idem | E11: Taux de droit commun
A12: IMF | B12: Exonération | C12: Exonération pendant 7 ans ou moitié de la durée d'exploitation | D12: idem | E12: idem
A13: Patente, TPA, TBM | B13: Exonération | C13: Exonération pendant 7 ans ou moitié de la durée d'exploitation | D13: idem | E13: idem | K13: Synthèse de l'évaluation du système fiscal
A14: Droits et taxes de douanes | B14: 0.025 | C14: 0.075 | D14: idem | E14: idem | K14: Critères | L14: Niveau | M14: Acteur concerné
K15: Efficacité | M15: Etat
C16: Taux d'actualisation 5% | F16: Taux d'actualisation 10% | I16: Elasticité du TEMI par rapport au TRI | K16: Progessivité | M16: Etat
B17: Cours de l'Or | C17: 1100 | D17: 1300 | E17: 1600 | F17: 1100 | G17: 1300 | H17: 1600 | K17: Transparence | M17: Etat
A18: Avant impôts | B18: VAN | C18: 1.3182213e+08 | D18: 3.5817536e+08 | E18: 6.9770521e+08 | F18: 45127855 | G18: 2.1488259e+08 | H18: 4.695147e+08 | K18: Partage de risque | M18: Etat
B19: TRI | C19: 0.13994104 | D19: 0.27738179 | E19: 0.45818507 | F19: 0.13994104 | G19: 0.27738179 | H19: 0.45818507 | K19: Développement local | M19: Etat
K20: Environnement | M20: Etat
A21: Après impôts | B21: VAN | C21: 24593413 | D21: 1.8131126e+08 | E21: 4.0820208e+08 | F21: -32756435 | G21: 84810341 | H21: 2.5496825e+08 | K21: Génération futures | M21: Etat
B22: TRI | C22: 0.068429663 | D22: 0.1760666 | E22: 0.31152275 | F22: 0.068429663 | G22: 0.1760666 | H22: 0.31152275 | K22: Lutte optimisation | M22: Etat
B23: TEMI | C23: 0.81343486 | D23: 0.49379191 | E23: 0.41493617 | F23: 1.7258584 | G23: 0.60531777 | H23: 0.45695365 | I23: =((H23-G23)/G23)/((H22-G22)/G22) -> -0.31858384 | K23: Neutralité | M23: Investisseur
C29: Taux d'actualisation 5% | F29: Taux d'actualisation 10% | I29: Elasticité du TEMI par rapport au TRI
B30: Cours de l'Or | C30: 1100 | D30: 1300 | E30: 1600 | F30: 1100 | G30: 1300 | H30: 1600
A31: Avant impôts | B31: VAN | C31: 1.3182213e+08 | D31: 3.5817536e+08 | E31: 6.9770521e+08 | F31: 45127855 | G31: 2.1488259e+08 | H31: 4.695147e+08
B32: TRI | C32: 0.13994104 | D32: 0.27738179 | E32: 0.45818507 | F32: 0.13994104 | G32: 0.27738179 | H32: 0.45818507
A34: Après impôts | B34: VAN | C34: 1475084.9 | D34: 1.4052529e+08 | E34: 3.3783723e+08 | F34: -49384053 | G34: 54946110 | H34: 2.0292118e+08
B35: TRI | C35: 0.051137873 | D35: 0.15060915 | E35: 0.27309616 | F35: 0.051137873 | G35: 0.15060915 | H35: 0.27309616
B36: TEMI | C36: 0.98881004 | D36: 0.60766343 | E36: 0.51578801 | F36: 2.0943142 | G36: 0.74429707 | H36: 0.56780654 | I36: =((H36-G36)/G36)/((H35-G35)/G35) -> -0.29156567
C43: Taux d'actualisation 5% | F43: Taux d'actualisation 10%
B44: Cours de l'Or | C44: 1100 | D44: 1300 | E44: 1600 | F44: 1100 | G44: 1300 | H44: 1600
A45: Avant impôts | B45: VAN | C45: 1.3182213e+08 | D45: 3.5817536e+08 | E45: 6.9770521e+08 | F45: 45127855 | G45: 2.1488259e+08 | H45: 4.695147e+08
B46: TRI | C46: 0.13994104 | D46: 0.27738179 | E46: 0.45818507 | F46: 0.13994104 | G46: 0.27738179 | H46: 0.45818507
A48: Après impôts | B48: VAN | C48: -11433766 | D48: 1.4052529e+08 | E48: 3.4925998e+08 | F48: -58555691 | G48: 52487256 | H48: 2.1198881e+08
B49: TRI | C49: 0.041002242 | D49: 0.15060915 | E49: 0.28111476 | F49: 0.041002242 | G49: 0.1487911 | H49: 0.28111476
B50: TEMI | C50: 1.0867363 | D50: 0.60766343 | E50: 0.49941613 | F50: 2.2975509 | G50: 0.75573985 | H50: 0.54849378

Sheet Modèle de base (CM 2003)
A1: Projet aurifère_De Houndé | B1: Unités | C1: 2011 | D1: 2012 | E1: 2013 | F1: 2014 | G1: 2015 | H1: 2016 | I1: 2017 | J1: 2018 | K1: 2019 | L1: 2020 | M1: 2021
A4: Production
A5: Quantité Traité | B5: t
A6: Teneur en or | B6: g/t
A7: Quantité d'Or Récupéré | B7: oz | E7: 191176 | F7: 215238 | G7: 189807 | H7: 168325 | I7: 210971 | J7: 167700 | K7: 136799 | L7: 152798 | M7: 119370 | N7: =AVERAGE(E7:M7) -> 172464.89 | Q7: Données | R7: VAN AV IMPÔT | S7: VAN AP IMPÔT | T7: TEMI | U7: TRI AV | V7: TRI AP
A8: Cours de l'or | B8: =Q8 -> 1600 | E8: 1300 | F8: 1300 | G8: 1300 | H8: 1300 | I8: 1300 | J8: 1300 | K8: 1300 | L8: 1300 | M8: 1300 | P8: Cours de l'or | Q8: 1600 | R8: =C26 -> 6.9770521e+08 | S8: =C55 -> 3.0445938e+08 | T8: =C56 -> 0.56362749 | U8: =C27 -> 0.45818507 | V8: =C57 -> 0.2547242
A9: Chiffre d'Affaire | B9: $ | E9: =E7*$B$8 -> 305881600 | F9: =F7*$B$8 -> 344380800 | G9: =G7*$B$8 -> 303691200 | H9: =H7*$B$8 -> 269320000 | I9: =I7*$B$8 -> 337553600 | J9: =J7*$B$8 -> 268320000 | K9: =K7*$B$8 -> 218878400 | L9: =L7*$B$8 -> 244476800 | M9: =M7*$B$8 -> 190992000 | P9: Taux d'actualisation | Q9: 0.05
A10: Taux de change | B10: 493.00615 | P10: IS | Q10: 0.35
A11: Taux d'actualisation | B11: =Q9 -> 0.05 | P11: Taux de redevance propotionelle | Q11: 0.04
A13: Coûts d'investissement (CAPEX)
A14: Coûts des construction industrielles | B14: $ | C14: 49760265 | D14: 116107284
A15: Coûts des biens d'équipement | C15: 23685527 | D15: 125300533 | E15: 11632917 | F15: 3722927 | G15: 18272647 | H15: 4482500 | I15: 2137128 | J15: 1103055 | K15: 4934651 | L15: 2727670 | M15: 542926
A16: Autres depenses | B16: $ | C16: 0 | D16: 0 | E16: 1595000 | F16: 2708200 | G16: 249700 | H16: 2581553 | I16: 469553 | J16: 3654542 | K16: 249700 | L16: 106700 | M16: 0
A17: Coûts de réhabilitation du site | B17: $ | E17: 2830244 | F17: 3314368 | G17: 3215137 | H17: 3842412 | I17: 4018506 | J17: 2935298 | K17: 1813443 | L17: 1249254 | M17: 3165512
A18: TOTAL CAPITAL | B18: $ | C18: =SUM(C14:C17) -> 73445792 | D18: =SUM(D14:D17) -> 241407817 | E18: =SUM(E14:E17) -> 16058161 | F18: =SUM(F14:F17) -> 9745495 | G18: =SUM(G14:G17) -> 21737484 | H18: =SUM(H14:H17) -> 10906465 | I18: =SUM(I14:I17) -> 6625187 | J18: =SUM(J14:J17) -> 7692895 | ... M18: =SUM(M14:M17) -> 3708438
A20: Coûts d'exploitation (Opex)/hors redevance | B20: $ | C20: 0 | D20: 0 | E20: 115668594 | F20: 128519703 | G20: 131246978 | H20: 152348402 | I20: 157632470 | J20: 132358509 | K20: 107272479 | L20: 96975692 | M20: 9542514
A21: Coûts d'exploitation moyen (Opex) /hors redevance | B21: $/oz | E21: =E20/E7 -> 605.03721 | F21: =F20/F7 -> 597.10508 | G21: =G20/G7 -> 691.47596 | H21: =H20/H7 -> 905.08482 | I21: =I20/I7 -> 747.17601 | J21: =J20/J7 -> 789.25766 | K21: =K20/K7 -> 784.16128 | L21: =L20/L7 -> 634.66598 | M21: =M20/M7 -> 79.940638
A23: Coût Totaux | C23: =C18+C20 -> 73445792 | D23: =D18+D20 -> 241407817 | E23: =E18+E20 -> 131726755 | F23: =F18+F20 -> 138265198 | G23: =G18+G20 -> 152984462 | H23: =H18+H20 -> 163254867 | I23: =I18+I20 -> 164257657 | J23: =J18+J20 -> 140051404 | ... M23: =M18+M20 -> 13250952
A25: Cash-flows avant impôts | C25: =C9-C23 -> -73445792 | D25: =D9-D23 -> -241407817 | E25: =E9-E23 -> 174154845 | F25: =F9-F23 -> 206115602 | G25: =G9-G23 -> 150706738 | H25: =H9-H23 -> 106065133 | I25: =I9-I23 -> 173295943 | J25: =J9-J23 -> 128268596 | ... M25: =M9-M23 -> 177741048
A26: VAN avant impôts | C26: =NPV($B$11,C25:M25) -> 6.9770521e+08
A27: TRI avant impôts | C27: =IRR(C25:M25) -> 0.45818507 | E27: =IRR($C$25:E25) -> -0.3913088 | F27: =IRR($C$25:F25) -> 0.11243079 | G27: =IRR($C$25:G25) -> 0.2768997 | H27: =IRR($C$25:H25) -> 0.3407976 | I27: =IRR($C$25:I25) -> 0.40012659 | J27: =IRR($C$25:J25) -> 0.42540794 | K27: =IRR($C$25:K25) -> 0.43824983 | L27: =IRR($C$25:L25) -> 0.44942432 | M27: =IRR($C$25:M25) -> 0.45818507
A29: Droits fixes | B29: 5000000 | C29: =B29/B10 -> 10141.861
A32: Superficie de la mine | C32: 23.2 | D32: 23.2 | E32: 23.2 | F32: 23.2 | G32: 23.2 | H32: 23.2 | I32: 23.2 | J32: 23.2 | K32: 23.2 | L32: 23.2 | M32: 23.2
A33: Redevance superficière | C33: =('Données fiscales'!C58/'Modèle de base (CM 2003)'!$B$10)*'Modèle de base (CM 2003)'!C32 -> 352936.77 | D33: =('Données fiscales'!D58/'Modèle de base (CM 2003)'!$B$10)*'Modèle de base (CM 2003)'!D32 -> 352936.77 | E33: =('Données fiscales'!E58/'Modèle de base (CM 2003)'!$B$10)*'Modèle de base (CM 2003)'!E32 -> 352936.77 | F33: =('Données fiscales'!F58/'Modèle de base (CM 2003)'!$B$10)*'Modèle de base (CM 2003)'!F32 -> 352936.77 | G33: =('Données fiscales'!G58/'Modèle de base (CM 2003)'!$B$10)*'Modèle de base (CM 2003)'!G32 -> 352936.77 | H33: =('Données fiscales'!H58/'Modèle de base (CM 2003)'!$B$10)*'Modèle de base (CM 2003)'!H32 -> 470582.36 | I33: =('Données fiscales'!I58/'Modèle de base (CM 2003)'!$B$10)*'Modèle de base (CM 2003)'!I32 -> 470582.36 | J33: =('Données fiscales'!J58/'Modèle de base (CM 2003)'!$B$10)*'Modèle de base (CM 2003)'!J32 -> 470582.36 | ... M33: =('Données fiscales'!M58/'Modèle de base (CM 2003)'!$B$10)*'Modèle de base (CM 2003)'!M32 -> 705873.55
A35: Redevance proportionnelle
A36: taux de la redevance | B36: =Q11 -> 0.04 | E36: ='Données fiscales'!E59 -> 0.04 | F36: ='Données fiscales'!F59 -> 0.04 | G36: ='Données fiscales'!G59 -> 0.04 | H36: ='Données fiscales'!H59 -> 0.04 | I36: ='Données fiscales'!I59 -> 0.04 | J36: ='Données fiscales'!J59 -> 0.04 | K36: ='Données fiscales'!K59 -> 0.04 | L36: ='Données fiscales'!L59 -> 0.04 | M36: ='Données fiscales'!M59 -> 0.04
A37: Montant de la redevance | C37: =$B$36*C9 -> 0 | D37: =$B$36*D9 -> 0 | E37: =$B$36*E9 -> 12235264 | F37: =$B$36*F9 -> 13775232 | G37: =$B$36*G9 -> 12147648 | H37: =$B$36*H9 -> 10772800 | I37: =$B$36*I9 -> 13502144 | J37: =$B$36*J9 -> 10732800 | ... M37: =$B$36*M9 -> 7639680
A39: Charges d'amortissement | C39: =Amortissement!C122 -> 14450237 | D39: =Amortissement!D122 -> 72391495 | E39: =Amortissement!E122 -> 54722766 | F39: =Amortissement!F122 -> 41469139 | G39: =Amortissement!G122 -> 42554951 | H39: =Amortissement!H122 -> 38090104 | I39: =Amortissement!I122 -> 22807098 | J39: =Amortissement!J122 -> 20561890 | ... M39: =Amortissement!M122 -> 15427244
A41: Bénéfice imposable | C41: =C$9-(C$23+C$29+C$33+C$37+C$39) -> -88259108 | D41: =D$9-(D$23+D$29+D$33+D$37+D$39) -> -3.1415225e+08 | E41: =E$9-(E$23+E$29+E$33+E$37+E$39) -> 1.0684388e+08 | F41: =F$9-(F$23+F$29+F$33+F$37+F$39) -> 1.5051829e+08 | G41: =G$9-(G$23+G$29+G$33+G$37+G$39) -> 95651203 | H41: =H$9-(H$23+H$29+H$33+H$37+H$39) -> 56731646 | I41: =I$9-(I$23+I$29+I$33+I$37+I$39) -> 1.3651612e+08 | J41: =J$9-(J$23+J$29+J$33+J$37+J$39) -> 96503324 | ... M41: =M$9-(M$23+M$29+M$33+M$37+M$39) -> 1.5396825e+08
A42: Taux IS | B42: =Q10 -> 0.35 | E42: ='Données fiscales'!E35 -> 0.175 | F42: ='Données fiscales'!F35 -> 0.175 | G42: ='Données fiscales'!G35 -> 0.175 | H42: ='Données fiscales'!H35 -> 0.175 | I42: ='Données fiscales'!I35 -> 0.175 | J42: ='Données fiscales'!J35 -> 0.175 | K42: ='Données fiscales'!K35 -> 0.175 | L42: ='Données fiscales'!L35 -> 0.175 | M42: ='Données fiscales'!M35 -> 0.175
A43: Montant IMF | J43: =0.5%*J9 -> 1341600 | K43: =0.5%*K9 -> 1094392 | L43: =0.5%*L9 -> 1222384 | M43: =0.5%*M9 -> 954960
A44: IS/IMF | C44: =IF(C$41*$B$42>C$43,C$41*$B$42,C$43) -> 0 | D44: =IF(D$41*$B$42>D$43,D$41*$B$42,D$43) -> 0 | E44: =IF(E$41*$B$42>E$43,E$41*$B$42,E$43) -> 37395358 | F44: =IF(F$41*$B$42>F$43,F$41*$B$42,F$43) -> 52681403 | G44: =IF(G$41*$B$42>G$43,G$41*$B$42,G$43) -> 33477921 | H44: =IF(H$41*$B$42>H$43,H$41*$B$42,H$43) -> 19856076 | I44: =IF(I$41*$B$42>I$43,I$41*$B$42,I$43) -> 47780641 | J44: =IF(J$41*$B$42>J$43,J$41*$B$42,J$43) -> 33776163 | ... M44: =IF(M$41*$B$42>M$43,M$41*$B$42,M$43) -> 53888888
A46: Résultat après impôt | C46: =C41-C44 -> -88259108 | D46: =D41-D44 -> -3.1415225e+08 | E46: =E41-E44 -> 69448521 | F46: =F41-F44 -> 97836891 | G46: =G41-G44 -> 62173282 | H46: =H41-H44 -> 36875570 | I46: =I41-I44 -> 88735477 | J46: =J41-J44 -> 62727161 | ... M46: =M41-M44 -> 1.0007936e+08
A47: Participation de l'Etat | B47: 0.1
A48: Dividende de l'Etat | C48: =IF(C46>0,C46*$B$47,0) -> 0 | D48: =IF(D46>0,D46*$B$47,0) -> 0 | E48: =IF(E46>0,E46*$B$47,0) -> 6944852.1 | F48: =IF(F46>0,F46*$B$47,0) -> 9783689.1 | G48: =IF(G46>0,G46*$B$47,0) -> 6217328.2 | H48: =IF(H46>0,H46*$B$47,0) -> 3687557 | I48: =IF(I46>0,I46*$B$47,0) -> 8873547.7 | J48: =IF(J46>0,J46*$B$47,0) -> 6272716.1 | ... M48: =IF(M46>0,M46*$B$47,0) -> 10007936
A49: Part de la société | C49: =C46-C48 -> -88259108 | D49: =D46-D48 -> -3.1415225e+08 | E49: =E46-E48 -> 62503669 | F49: =F46-F48 -> 88053202 | G49: =G46-G48 -> 55955953 | H49: =H46-H48 -> 33188013 | I49: =I46-I48 -> 79861929 | J49: =J46-J48 -> 56454445 | ... M49: =M46-M48 -> 90071426
A50: Impôt sur les dividendes | C50: =IF(C49>0,C49*'Données fiscales'!C40,0) -> 0 | D50: =IF(D49>0,D49*'Données fiscales'!D40,0) -> 0 | E50: =IF(E49>0,E49*'Données fiscales'!E40,0) -> 3906479.3 | F50: =IF(F49>0,F49*'Données fiscales'!F40,0) -> 5503325.1 | G50: =IF(G49>0,G49*'Données fiscales'!G40,0) -> 3497247.1 | H50: =IF(H49>0,H49*'Données fiscales'!H40,0) -> 2074250.8 | I50: =IF(I49>0,I49*'Données fiscales'!I40,0) -> 4991370.6 | J50: =IF(J49>0,J49*'Données fiscales'!J40,0) -> 3528402.8 | ... M50: =IF(M49>0,M49*'Données fiscales'!M40,0) -> 5629464.1
A53: Recettes totales de l'Etat | C53: =C$29+C$33+C$37+C$44+C$48+C$50 -> 363078.64 | D53: =D$29+D$33+D$37+D$44+D$48+D$50 -> 352936.77 | E53: =E$29+E$33+E$37+E$44+E$48+E$50 -> 60834890 | F53: =F$29+F$33+F$37+F$44+F$48+F$50 -> 82096586 | G53: =G$29+G$33+G$37+G$44+G$48+G$50 -> 55693081 | H53: =H$29+H$33+H$37+H$44+H$48+H$50 -> 36861266 | I53: =I$29+I$33+I$37+I$44+I$48+I$50 -> 75618286 | J53: =J$29+J$33+J$37+J$44+J$48+J$50 -> 54780665 | ... M53: =M$29+M$33+M$37+M$44+M$48+M$50 -> 77871841
A54: Cash-Flows après imôts | C54: =C25-C53 -> -73808871 | D54: =D25-D53 -> -2.4176075e+08 | E54: =E25-E53 -> 1.1331996e+08 | F54: =F25-F53 -> 1.2401902e+08 | G54: =G25-G53 -> 95013657 | H54: =H25-H53 -> 69203867 | I54: =I25-I53 -> 97677657 | J54: =J25-J53 -> 73487931 | ... M54: =M25-M53 -> 99869207
A55: VAN après impôts | C55: =NPV($B$11,C54:M54) -> 3.0445938e+08
A56: TEMI | C56: =1-(C55/C26) -> 0.56362749
A57: TRI après impôts | C57: =IRR(C54:M54) -> 0.2547242 | F57: =IRR($C$54:F54) -> -0.1492555 | G57: =IRR($C$54:G54) -> 0.024126629 | H57: =IRR($C$54:H54) -> 0.10169092 | I57: =IRR($C$54:I54) -> 0.17018122 | J57: =IRR($C$54:J54) -> 0.20296263 | K57: =IRR($C$54:K54) -> 0.2221153 | L57: =IRR($C$54:L54) -> 0.23986363 | M57: =IRR($C$54:M54) -> 0.2547242
A58: Part de la société | C58: =1-C56 -> 0.43637251

Sheet Code Minier 2015
A1: Projet aurifère_De Houndé | B1: Unités | C1: ='Modèle de base (CM 2003)'!C1 -> 2011 | D1: ='Modèle de base (CM 2003)'!D1 -> 2012 | E1: ='Modèle de base (CM 2003)'!E1 -> 2013 | F1: ='Modèle de base (CM 2003)'!F1 -> 2014 | G1: ='Modèle de base (CM 2003)'!G1 -> 2015 | H1: ='Modèle de base (CM 2003)'!H1 -> 2016 | I1: ='Modèle de base (CM 2003)'!I1 -> 2017 | J1: ='Modèle de base (CM 2003)'!J1 -> 2018 | ... M1: ='Modèle de base (CM 2003)'!M1 -> 2021
C2: ='Modèle de base (CM 2003)'!C2 -> 0 | D2: ='Modèle de base (CM 2003)'!D2 -> 0 | E2: ='Modèle de base (CM 2003)'!E2 -> 0 | F2: ='Modèle de base (CM 2003)'!F2 -> 0 | G2: ='Modèle de base (CM 2003)'!G2 -> 0 | H2: ='Modèle de base (CM 2003)'!H2 -> 0 | I2: ='Modèle de base (CM 2003)'!I2 -> 0 | J2: ='Modèle de base (CM 2003)'!J2 -> 0 | ... M2: ='Modèle de base (CM 2003)'!M2 -> 0
C3: ='Modèle de base (CM 2003)'!C3 -> 0 | D3: ='Modèle de base (CM 2003)'!D3 -> 0 | E3: ='Modèle de base (CM 2003)'!E3 -> 0 | F3: ='Modèle de base (CM 2003)'!F3 -> 0 | G3: ='Modèle de base (CM 2003)'!G3 -> 0 | H3: ='Modèle de base (CM 2003)'!H3 -> 0 | I3: ='Modèle de base (CM 2003)'!I3 -> 0 | J3: ='Modèle de base (CM 2003)'!J3 -> 0 | ... M3: ='Modèle de base (CM 2003)'!M3 -> 0
A4: Production | C4: ='Modèle de base (CM 2003)'!C4 -> 0 | D4: ='Modèle de base (CM 2003)'!D4 -> 0 | E4: ='Modèle de base (CM 2003)'!E4 -> 0 | F4: ='Modèle de base (CM 2003)'!F4 -> 0 | G4: ='Modèle de base (CM 2003)'!G4 -> 0 | H4: ='Modèle de base (CM 2003)'!H4 -> 0 | I4: ='Modèle de base (CM 2003)'!I4 -> 0 | J4: ='Modèle de base (CM 2003)'!J4 -> 0 | ... M4: ='Modèle de base (CM 2003)'!M4 -> 0
A5: Quantité Traité | B5: t | C5: ='Modèle de base (CM 2003)'!C5 -> 0 | D5: ='Modèle de base (CM 2003)'!D5 -> 0 | E5: ='Modèle de base (CM 2003)'!E5 -> 0 | F5: ='Modèle de base (CM 2003)'!F5 -> 0 | G5: ='Modèle de base (CM 2003)'!G5 -> 0 | H5: ='Modèle de base (CM 2003)'!H5 -> 0 | I5: ='Modèle de base (CM 2003)'!I5 -> 0 | J5: ='Modèle de base (CM 2003)'!J5 -> 0 | ... M5: ='Modèle de base (CM 2003)'!M5 -> 0
A6: Teneur en or | B6: g/t | C6: ='Modèle de base (CM 2003)'!C6 -> 0 | D6: ='Modèle de base (CM 2003)'!D6 -> 0 | E6: ='Modèle de base (CM 2003)'!E6 -> 0 | F6: ='Modèle de base (CM 2003)'!F6 -> 0 | G6: ='Modèle de base (CM 2003)'!G6 -> 0 | H6: ='Modèle de base (CM 2003)'!H6 -> 0 | I6: ='Modèle de base (CM 2003)'!I6 -> 0 | J6: ='Modèle de base (CM 2003)'!J6 -> 0 | ... M6: ='Modèle de base (CM 2003)'!M6 -> 0
A7: Quantité d'Or Récupéré | B7: oz | C7: ='Modèle de base (CM 2003)'!C7 -> 0 | D7: ='Modèle de base (CM 2003)'!D7 -> 0 | E7: ='Modèle de base (CM 2003)'!E7 -> 191176 | F7: ='Modèle de base (CM 2003)'!F7 -> 215238 | G7: ='Modèle de base (CM 2003)'!G7 -> 189807 | H7: ='Modèle de base (CM 2003)'!H7 -> 168325 | I7: ='Modèle de base (CM 2003)'!I7 -> 210971 | J7: ='Modèle de base (CM 2003)'!J7 -> 167700 | ... M7: ='Modèle de base (CM 2003)'!M7 -> 119370
A8: Cours de l'or | B8: =Q10 -> 1300 | C8: ='Modèle de base (CM 2003)'!C8 -> 0 | D8: ='Modèle de base (CM 2003)'!D8 -> 0 | E8: ='Modèle de base (CM 2003)'!E8 -> 1300 | F8: ='Modèle de base (CM 2003)'!F8 -> 1300 | G8: ='Modèle de base (CM 2003)'!G8 -> 1300 | H8: ='Modèle de base (CM 2003)'!H8 -> 1300 | I8: ='Modèle de base (CM 2003)'!I8 -> 1300 | J8: ='Modèle de base (CM 2003)'!J8 -> 1300 | ... M8: ='Modèle de base (CM 2003)'!M8 -> 1300
A9: Chiffre d'Affaire | B9: $ | C9: =$B$8*C7 -> 0 | D9: =$B$8*D7 -> 0 | E9: =$B$8*E7 -> 248528800 | F9: =$B$8*F7 -> 279809400 | G9: =$B$8*G7 -> 246749100 | H9: =$B$8*H7 -> 218822500 | I9: =$B$8*I7 -> 274262300 | J9: =$B$8*J7 -> 218010000 | ... M9: =$B$8*M7 -> 155181000 | Q9: Données | R9: VAN AV IMPÔT | S9: VAN AP IMPÔT | T9: TEMI | U9: TRI AV | V9: TRI AP
A10: Taux de change | B10: 602.60042 | C10: ='Modèle de base (CM 2003)'!C10 -> 0 | D10: ='Modèle de base (CM 2003)'!D10 -> 0 | E10: ='Modèle de base (CM 2003)'!E10 -> 0 | F10: ='Modèle de base (CM 2003)'!F10 -> 0 | G10: ='Modèle de base (CM 2003)'!G10 -> 0 | H10: ='Modèle de base (CM 2003)'!H10 -> 0 | I10: ='Modèle de base (CM 2003)'!I10 -> 0 | J10: ='Modèle de base (CM 2003)'!J10 -> 0 | ... M10: ='Modèle de base (CM 2003)'!M10 -> 0 | P10: Cours de l'or | Q10: 1300 | R10: =C26 -> 3.5817536e+08 | S10: =C56 -> 1.4052529e+08 | T10: =C57 -> 0.60766343 | U10: =C27 -> 0.27738179 | V10: =C58 -> 0.15060915
A11: Taux d'actualisation | B11: =Q11 -> 0.05 | C11: ='Modèle de base (CM 2003)'!C11 -> 0 | D11: ='Modèle de base (CM 2003)'!D11 -> 0 | E11: ='Modèle de base (CM 2003)'!E11 -> 0 | F11: ='Modèle de base (CM 2003)'!F11 -> 0 | G11: ='Modèle de base (CM 2003)'!G11 -> 0 | H11: ='Modèle de base (CM 2003)'!H11 -> 0 | I11: ='Modèle de base (CM 2003)'!I11 -> 0 | J11: ='Modèle de base (CM 2003)'!J11 -> 0 | ... M11: ='Modèle de base (CM 2003)'!M11 -> 0 | P11: Taux d'actualisation | Q11: 0.05
C12: ='Modèle de base (CM 2003)'!C12 -> 0 | D12: ='Modèle de base (CM 2003)'!D12 -> 0 | E12: ='Modèle de base (CM 2003)'!E12 -> 0 | F12: ='Modèle de base (CM 2003)'!F12 -> 0 | G12: ='Modèle de base (CM 2003)'!G12 -> 0 | H12: ='Modèle de base (CM 2003)'!H12 -> 0 | I12: ='Modèle de base (CM 2003)'!I12 -> 0 | J12: ='Modèle de base (CM 2003)'!J12 -> 0 | ... M12: ='Modèle de base (CM 2003)'!M12 -> 0 | P12: IS | Q12: 0.275
A13: Coûts d'investissement (CAPEX) | C13: ='Modèle de base (CM 2003)'!C13 -> 0 | D13: ='Modèle de base (CM 2003)'!D13 -> 0 | E13: ='Modèle de base (CM 2003)'!E13 -> 0 | F13: ='Modèle de base (CM 2003)'!F13 -> 0 | G13: ='Modèle de base (CM 2003)'!G13 -> 0 | H13: ='Modèle de base (CM 2003)'!H13 -> 0 | I13: ='Modèle de base (CM 2003)'!I13 -> 0 | J13: ='Modèle de base (CM 2003)'!J13 -> 0 | ... M13: ='Modèle de base (CM 2003)'!M13 -> 0 | P13: Taux de redevance propotionelle | Q13: 0.04
A14: Coûts des construction industrielles | B14: $ | C14: ='Modèle de base (CM 2003)'!C14 -> 49760265 | D14: ='Modèle de base (CM 2003)'!D14 -> 116107284 | E14: ='Modèle de base (CM 2003)'!E14 -> 0 | F14: ='Modèle de base (CM 2003)'!F14 -> 0 | G14: ='Modèle de base (CM 2003)'!G14 -> 0 | H14: ='Modèle de base (CM 2003)'!H14 -> 0 | I14: ='Modèle de base (CM 2003)'!I14 -> 0 | J14: ='Modèle de base (CM 2003)'!J14 -> 0 | ... M14: ='Modèle de base (CM 2003)'!M14 -> 0
A15: Coûts des biens d'équipement | C15: ='Modèle de base (CM 2003)'!C15 -> 23685527 | D15: ='Modèle de base (CM 2003)'!D15 -> 125300533 | E15: ='Modèle de base (CM 2003)'!E15 -> 11632917 | F15: ='Modèle de base (CM 2003)'!F15 -> 3722927 | G15: ='Modèle de base (CM 2003)'!G15 -> 18272647 | H15: ='Modèle de base (CM 2003)'!H15 -> 4482500 | I15: ='Modèle de base (CM 2003)'!I15 -> 2137128 | J15: ='Modèle de base (CM 2003)'!J15 -> 1103055 | ... M15: ='Modèle de base (CM 2003)'!M15 -> 542926
A16: Autres depenses | B16: $ | C16: ='Modèle de base (CM 2003)'!C16 -> 0 | D16: ='Modèle de base (CM 2003)'!D16 -> 0 | E16: ='Modèle de base (CM 2003)'!E16 -> 1595000 | F16: ='Modèle de base (CM 2003)'!F16 -> 2708200 | G16: ='Modèle de base (CM 2003)'!G16 -> 249700 | H16: ='Modèle de base (CM 2003)'!H16 -> 2581553 | I16: ='Modèle de base (CM 2003)'!I16 -> 469553 | J16: ='Modèle de base (CM 2003)'!J16 -> 3654542 | ... M16: ='Modèle de base (CM 2003)'!M16 -> 0
A17: Coûts de réhabilitation du site | B17: $ | C17: ='Modèle de base (CM 2003)'!C17 -> 0 | D17: ='Modèle de base (CM 2003)'!D17 -> 0 | E17: ='Modèle de base (CM 2003)'!E17 -> 2830244 | F17: ='Modèle de base (CM 2003)'!F17 -> 3314368 | G17: ='Modèle de base (CM 2003)'!G17 -> 3215137 | H17: ='Modèle de base (CM 2003)'!H17 -> 3842412 | I17: ='Modèle de base (CM 2003)'!I17 -> 4018506 | J17: ='Modèle de base (CM 2003)'!J17 -> 2935298 | ... M17: ='Modèle de base (CM 2003)'!M17 -> 3165512
A18: TOTAL CAPITAL | B18: $ | C18: =SUM(C14:C17) -> 73445792 | D18: =SUM(D14:D17) -> 241407817 | E18: =SUM(E14:E17) -> 16058161 | F18: =SUM(F14:F17) -> 9745495 | G18: =SUM(G14:G17) -> 21737484 | H18: =SUM(H14:H17) -> 10906465 | I18: =SUM(I14:I17) -> 6625187 | J18: =SUM(J14:J17) -> 7692895 | ... M18: =SUM(M14:M17) -> 3708438
C19: ='Modèle de base (CM 2003)'!C19 -> 0 | D19: ='Modèle de base (CM 2003)'!D19 -> 0 | E19: ='Modèle de base (CM 2003)'!E19 -> 0 | F19: ='Modèle de base (CM 2003)'!F19 -> 0 | G19: ='Modèle de base (CM 2003)'!G19 -> 0 | H19: ='Modèle de base (CM 2003)'!H19 -> 0 | I19: ='Modèle de base (CM 2003)'!I19 -> 0 | J19: ='Modèle de base (CM 2003)'!J19 -> 0 | ... M19: ='Modèle de base (CM 2003)'!M19 -> 0
A20: Coûts d'exploitation (Opex)/hors redevance | B20: $ | C20: ='Modèle de base (CM 2003)'!C20 -> 0 | D20: ='Modèle de base (CM 2003)'!D20 -> 0 | E20: ='Modèle de base (CM 2003)'!E20 -> 115668594 | F20: ='Modèle de base (CM 2003)'!F20 -> 128519703 | G20: ='Modèle de base (CM 2003)'!G20 -> 131246978 | H20: ='Modèle de base (CM 2003)'!H20 -> 152348402 | I20: ='Modèle de base (CM 2003)'!I20 -> 157632470 | J20: ='Modèle de base (CM 2003)'!J20 -> 132358509 | ... M20: ='Modèle de base (CM 2003)'!M20 -> 9542514
A21: Coûts d'exploitation moyen (Opex) /hors redevance | B21: $/oz | C21: ='Modèle de base (CM 2003)'!C21 -> 0 | D21: ='Modèle de base (CM 2003)'!D21 -> 0 | E21: ='Modèle de base (CM 2003)'!E21 -> 605.03721 | F21: ='Modèle de base (CM 2003)'!F21 -> 597.10508 | G21: ='Modèle de base (CM 2003)'!G21 -> 691.47596 | H21: ='Modèle de base (CM 2003)'!H21 -> 905.08482 | I21: ='Modèle de base (CM 2003)'!I21 -> 747.17601 | J21: ='Modèle de base (CM 2003)'!J21 -> 789.25766 | ... M21: ='Modèle de base (CM 2003)'!M21 -> 79.940638
C22: ='Modèle de base (CM 2003)'!C22 -> 0 | D22: ='Modèle de base (CM 2003)'!D22 -> 0 | E22: ='Modèle de base (CM 2003)'!E22 -> 0 | F22: ='Modèle de base (CM 2003)'!F22 -> 0 | G22: ='Modèle de base (CM 2003)'!G22 -> 0 | H22: ='Modèle de base (CM 2003)'!H22 -> 0 | I22: ='Modèle de base (CM 2003)'!I22 -> 0 | J22: ='Modèle de base (CM 2003)'!J22 -> 0 | ... M22: ='Modèle de base (CM 2003)'!M22 -> 0
A23: Coût Totaux | C23: =C18+C20 -> 73445792 | D23: =D18+D20 -> 241407817 | E23: =E18+E20 -> 131726755 | F23: =F18+F20 -> 138265198 | G23: =G18+G20 -> 152984462 | H23: =H18+H20 -> 163254867 | I23: =I18+I20 -> 164257657 | J23: =J18+J20 -> 140051404 | ... M23: =M18+M20 -> 13250952
C24: ='Modèle de base (CM 2003)'!C24 -> 0 | D24: ='Modèle de base (CM 2003)'!D24 -> 0 | E24: ='Modèle de base (CM 2003)'!E24 -> 0 | F24: ='Modèle de base (CM 2003)'!F24 -> 0 | G24: ='Modèle de base (CM 2003)'!G24 -> 0 | H24: ='Modèle de base (CM 2003)'!H24 -> 0 | I24: ='Modèle de base (CM 2003)'!I24 -> 0 | J24: ='Modèle de base (CM 2003)'!J24 -> 0 | ... M24: ='Modèle de base (CM 2003)'!M24 -> 0
A25: Cash-flows avant impôts | C25: =C$9-C$23 -> -73445792 | D25: =D$9-D$23 -> -241407817 | E25: =E$9-E$23 -> 116802045 | F25: =F$9-F$23 -> 141544202 | G25: =G$9-G$23 -> 93764638 | H25: =H$9-H$23 -> 55567633 | I25: =I$9-I$23 -> 110004643 | J25: =J$9-J$23 -> 77958596 | ... M25: =M$9-M$23 -> 141930048
A26: VAN avant impôts | C26: =NPV(B11,C25:M25) -> 3.5817536e+08 | D26: ='Modèle de base (CM 2003)'!D26 -> 0 | E26: ='Modèle de base (CM 2003)'!E26 -> 0 | F26: ='Modèle de base (CM 2003)'!F26 -> 0 | G26: ='Modèle de base (CM 2003)'!G26 -> 0 | H26: ='Modèle de base (CM 2003)'!H26 -> 0 | I26: ='Modèle de base (CM 2003)'!I26 -> 0 | J26: ='Modèle de base (CM 2003)'!J26 -> 0 | K26: ='Modèle de base (CM 2003)'!K26 -> 0 | ... M26: ='Modèle de base (CM 2003)'!M26 -> 0
A27: TRI avant impôts | C27: =IRR(C25:M25) -> 0.27738179
C28: ='Modèle de base (CM 2003)'!C28 -> 0
A29: Droits fixes | B29: 10000000 | C29: ='Données fiscales'!C89/'Code Minier 2015'!B10 -> 16594.744
C30: ='Modèle de base (CM 2003)'!C30 -> 0
C31: ='Modèle de base (CM 2003)'!C31 -> 0
A32: Superficie de la mine | C32: ='Modèle de base (CM 2003)'!C32 -> 23.2 | D32: ='Modèle de base (CM 2003)'!D32 -> 23.2 | E32: ='Modèle de base (CM 2003)'!E32 -> 23.2 | F32: ='Modèle de base (CM 2003)'!F32 -> 23.2 | G32: ='Modèle de base (CM 2003)'!G32 -> 23.2 | H32: ='Modèle de base (CM 2003)'!H32 -> 23.2 | I32: ='Modèle de base (CM 2003)'!I32 -> 23.2 | J32: ='Modèle de base (CM 2003)'!J32 -> 23.2 | ... M32: ='Modèle de base (CM 2003)'!M32 -> 23.2
A33: Redevance superficière | C33: ='Modèle de base (CM 2003)'!C33 -> 352936.77 | D33: ='Modèle de base (CM 2003)'!D33 -> 352936.77 | E33: ='Modèle de base (CM 2003)'!E33 -> 352936.77 | F33: ='Modèle de base (CM 2003)'!F33 -> 352936.77 | G33: ='Modèle de base (CM 2003)'!G33 -> 352936.77 | H33: ='Modèle de base (CM 2003)'!H33 -> 470582.36 | I33: ='Modèle de base (CM 2003)'!I33 -> 470582.36 | J33: ='Modèle de base (CM 2003)'!J33 -> 470582.36 | ... M33: ='Modèle de base (CM 2003)'!M33 -> 705873.55
C34: ='Modèle de base (CM 2003)'!C34 -> 0 | D34: ='Modèle de base (CM 2003)'!D34 -> 0 | E34: ='Modèle de base (CM 2003)'!E34 -> 0 | F34: ='Modèle de base (CM 2003)'!F34 -> 0 | G34: ='Modèle de base (CM 2003)'!G34 -> 0 | H34: ='Modèle de base (CM 2003)'!H34 -> 0 | I34: ='Modèle de base (CM 2003)'!I34 -> 0 | J34: ='Modèle de base (CM 2003)'!J34 -> 0 | ... M34: ='Modèle de base (CM 2003)'!M34 -> 0
A35: Redevance proportionnelle | C35: ='Modèle de base (CM 2003)'!C35 -> 0 | D35: ='Modèle de base (CM 2003)'!D35 -> 0 | E35: ='Modèle de base (CM 2003)'!E35 -> 0 | F35: ='Modèle de base (CM 2003)'!F35 -> 0 | G35: ='Modèle de base (CM 2003)'!G35 -> 0 | H35: ='Modèle de base (CM 2003)'!H35 -> 0 | I35: ='Modèle de base (CM 2003)'!I35 -> 0 | J35: ='Modèle de base (CM 2003)'!J35 -> 0 | ... M35: ='Modèle de base (CM 2003)'!M35 -> 0
A36: taux de la redevance | B36: =Q13 -> 0.04 | C36: ='Modèle de base (CM 2003)'!C36 -> 0 | D36: ='Modèle de base (CM 2003)'!D36 -> 0 | E36: ='Modèle de base (CM 2003)'!E36 -> 0.04 | F36: ='Modèle de base (CM 2003)'!F36 -> 0.04 | G36: ='Modèle de base (CM 2003)'!G36 -> 0.04 | H36: ='Modèle de base (CM 2003)'!H36 -> 0.04 | I36: ='Modèle de base (CM 2003)'!I36 -> 0.04 | J36: ='Modèle de base (CM 2003)'!J36 -> 0.04 | ... M36: ='Modèle de base (CM 2003)'!M36 -> 0.04
A37: Montant de la redevance | C37: =$B$36*C9 -> 0 | D37: =$B$36*D9 -> 0 | E37: =$B$36*E9 -> 9941152 | F37: =$B$36*F9 -> 11192376 | G37: =$B$36*G9 -> 9869964 | H37: =$B$36*H9 -> 8752900 | I37: =$B$36*I9 -> 10970492 | J37: =$B$36*J9 -> 8720400 | ... M37: =$B$36*M9 -> 6207240
C38: ='Modèle de base (CM 2003)'!C38 -> 0 | D38: ='Modèle de base (CM 2003)'!D38 -> 0 | E38: ='Modèle de base (CM 2003)'!E38 -> 0 | F38: ='Modèle de base (CM 2003)'!F38 -> 0 | G38: ='Modèle de base (CM 2003)'!G38 -> 0 | H38: ='Modèle de base (CM 2003)'!H38 -> 0 | I38: ='Modèle de base (CM 2003)'!I38 -> 0 | J38: ='Modèle de base (CM 2003)'!J38 -> 0 | ... M38: ='Modèle de base (CM 2003)'!M38 -> 0
A39: Charges d'amortissement | C39: ='Modèle de base (CM 2003)'!C39 -> 14450237 | D39: ='Modèle de base (CM 2003)'!D39 -> 72391495 | E39: ='Modèle de base (CM 2003)'!E39 -> 54722766 | F39: ='Modèle de base (CM 2003)'!F39 -> 41469139 | G39: ='Modèle de base (CM 2003)'!G39 -> 42554951 | H39: ='Modèle de base (CM 2003)'!H39 -> 38090104 | I39: ='Modèle de base (CM 2003)'!I39 -> 22807098 | J39: ='Modèle de base (CM 2003)'!J39 -> 20561890 | ... M39: ='Modèle de base (CM 2003)'!M39 -> 15427244
A40: Developpement local | C40: =C9*'Données fiscales'!C95 -> 0 | D40: =D9*'Données fiscales'!D95 -> 0 | E40: =E9*'Données fiscales'!E95 -> 2485288 | F40: =F9*'Données fiscales'!F95 -> 2798094 | G40: =G9*'Données fiscales'!G95 -> 2467491 | H40: =H9*'Données fiscales'!H95 -> 2188225 | I40: =I9*'Données fiscales'!I95 -> 2742623 | J40: =J9*'Données fiscales'!J95 -> 2180100 | ... M40: =M9*'Données fiscales'!M95 -> 1551810
A42: Bénéfice imposable | C42: =C9-(C$23+C$29+C$33+C$39+C$37+C$40) -> -88265561 | D42: =D9-(D$23+D$29+D$33+D$39+D$37+D$40) -> -3.1415225e+08 | E42: =E9-(E$23+E$29+E$33+E$39+E$37+E$40) -> 49299903 | F42: =F9-(F$23+F$29+F$33+F$39+F$37+F$40) -> 85731656 | G42: =G9-(G$23+G$29+G$33+G$39+G$37+G$40) -> 38519296 | H42: =H9-(H$23+H$29+H$33+H$39+H$37+H$40) -> 6065821.4 | I42: =I9-(I$23+I$29+I$33+I$39+I$37+I$40) -> 73013847 | J42: =J9-(J$23+J$29+J$33+J$39+J$37+J$40) -> 46025624 | ... M42: =M9-(M$23+M$29+M$33+M$39+M$37+M$40) -> 1.1803788e+08
A43: Taux IS | B43: =Q12 -> 0.275 | C43: ='Données fiscales'!C100 -> 0 | D43: ='Données fiscales'!D100 -> 0 | E43: ='Données fiscales'!E100 -> 0.275 | F43: ='Données fiscales'!F100 -> 0.275 | G43: ='Données fiscales'!G100 -> 0.275 | H43: ='Données fiscales'!H100 -> 0.275 | I43: ='Données fiscales'!I100 -> 0.275 | J43: ='Données fiscales'!J100 -> 0.275 | ... M43: ='Données fiscales'!M100 -> 0.275
A44: Montant IMF | C44: ='Modèle de base (CM 2003)'!C43 -> 0 | D44: ='Modèle de base (CM 2003)'!D43 -> 0 | E44: ='Modèle de base (CM 2003)'!E43 -> 0 | F44: ='Modèle de base (CM 2003)'!F43 -> 0 | G44: ='Modèle de base (CM 2003)'!G43 -> 0 | H44: ='Modèle de base (CM 2003)'!H43 -> 0 | I44: ='Modèle de base (CM 2003)'!I43 -> 0 | J44: ='Modèle de base (CM 2003)'!J43 -> 1341600 | ... M44: ='Modèle de base (CM 2003)'!M43 -> 954960
A45: IS/IMF | C45: =IF(C$42*$B$43>C$44,C$42*$B$43,0) -> 0 | D45: =IF(D$42*$B$43>D$44,D$42*$B$43,0) -> 0 | E45: =IF(E$42*$B$43>E$44,E$42*$B$43,0) -> 13557473 | F45: =IF(F$42*$B$43>F$44,F$42*$B$43,0) -> 23576205 | G45: =IF(G$42*$B$43>G$44,G$42*$B$43,0) -> 10592806 | H45: =IF(H$42*$B$43>H$44,H$42*$B$43,0) -> 1668100.9 | I45: =IF(I$42*$B$43>I$44,I$42*$B$43,0) -> 20078808 | J45: =IF(J$42*$B$43>J$44,J$42*$B$43,0) -> 12657047 | ... M45: =IF(M$42*$B$43>M$44,M$42*$B$43,0) -> 32460417
C46: ='Modèle de base (CM 2003)'!C45 -> 0 | D46: ='Modèle de base (CM 2003)'!D45 -> 0 | E46: ='Modèle de base (CM 2003)'!E45 -> 0 | F46: ='Modèle de base (CM 2003)'!F45 -> 0 | G46: ='Modèle de base (CM 2003)'!G45 -> 0 | H46: ='Modèle de base (CM 2003)'!H45 -> 0 | I46: ='Modèle de base (CM 2003)'!I45 -> 0 | J46: ='Modèle de base (CM 2003)'!J45 -> 0 | ... M46: ='Modèle de base (CM 2003)'!M45 -> 0
A47: Résultat après impôt | C47: =C$42-C$45 -> -88265561 | D47: =D$42-D$45 -> -3.1415225e+08 | E47: =E$42-E$45 -> 35742429 | F47: =F$42-F$45 -> 62155450 | G47: =G$42-G$45 -> 27926489 | H47: =H$42-H$45 -> 4397720.5 | I47: =I$42-I$45 -> 52935039 | J47: =J$42-J$45 -> 33368577 | ... M47: =M$42-M$45 -> 85577463
A48: Participation de l'Etat | B48: 0.1 | C48: ='Modèle de base (CM 2003)'!C47 -> 0 | D48: ='Modèle de base (CM 2003)'!D47 -> 0 | E48: ='Modèle de base (CM 2003)'!E47 -> 0 | F48: ='Modèle de base (CM 2003)'!F47 -> 0 | G48: ='Modèle de base (CM 2003)'!G47 -> 0 | H48: ='Modèle de base (CM 2003)'!H47 -> 0 | I48: ='Modèle de base (CM 2003)'!I47 -> 0 | J48: ='Modèle de base (CM 2003)'!J47 -> 0 | ... M48: ='Modèle de base (CM 2003)'!M47 -> 0
A49: Dividende de l'Etat | C49: =IF(C47>0,C47*$B$48,0) -> 0 | D49: =IF(D47>0,D47*$B$48,0) -> 0 | E49: =IF(E47>0,E47*$B$48,0) -> 3574242.9 | F49: =IF(F47>0,F47*$B$48,0) -> 6215545 | G49: =IF(G47>0,G47*$B$48,0) -> 2792648.9 | H49: =IF(H47>0,H47*$B$48,0) -> 439772.05 | I49: =IF(I47>0,I47*$B$48,0) -> 5293503.9 | J49: =IF(J47>0,J47*$B$48,0) -> 3336857.7 | ... M49: =IF(M47>0,M47*$B$48,0) -> 8557746.3
A50: Part de la société | C50: =C$47-C$49 -> -88265561 | D50: =D$47-D$49 -> -3.1415225e+08 | E50: =E$47-E$49 -> 32168187 | F50: =F$47-F$49 -> 55939905 | G50: =G$47-G$49 -> 25133840 | H50: =H$47-H$49 -> 3957948.4 | I50: =I$47-I$49 -> 47641535 | J50: =J$47-J$49 -> 30031720 | ... M50: =M$47-M$49 -> 77019717
A51: Impôt sur les dividendes | C51: =IF(C50>0,'Données fiscales'!C72*C50,0) -> 0 | D51: =IF(D50>0,'Données fiscales'!D72*D50,0) -> 0 | E51: =IF(E50>0,'Données fiscales'!E72*E50,0) -> 2010511.7 | F51: =IF(F50>0,'Données fiscales'!F72*F50,0) -> 3496244.1 | G51: =IF(G50>0,'Données fiscales'!G72*G50,0) -> 1570865 | H51: =IF(H50>0,'Données fiscales'!H72*H50,0) -> 247371.78 | I51: =IF(I50>0,'Données fiscales'!I72*I50,0) -> 2977596 | J51: =IF(J50>0,'Données fiscales'!J72*J50,0) -> 1876982.5 | ... M51: =IF(M50>0,'Données fiscales'!M72*M50,0) -> 4813732.3
A54: Recettes totales de l'Etat | C54: =C$29+C$33+C$37+C$40+C$45+C$49+C$51 -> 369531.52 | D54: =D$29+D$33+D$37+D$40+D$45+D$49+D$51 -> 352936.77 | E54: =E$29+E$33+E$37+E$40+E$45+E$49+E$51 -> 31921605 | F54: =F$29+F$33+F$37+F$40+F$45+F$49+F$51 -> 47631401 | G54: =G$29+G$33+G$37+G$40+G$45+G$49+G$51 -> 27646712 | H54: =H$29+H$33+H$37+H$40+H$45+H$49+H$51 -> 13766952 | I54: =I$29+I$33+I$37+I$40+I$45+I$49+I$51 -> 42533605 | J54: =J$29+J$33+J$37+J$40+J$45+J$49+J$51 -> 29241969 | ... M54: =M$29+M$33+M$37+M$40+M$45+M$49+M$51 -> 54296819
A55: Cash-Flows après imôts | C55: =C$25-C$54 -> -73815324 | D55: =D$25-D$54 -> -2.4176075e+08 | E55: =E$25-E$54 -> 84880440 | F55: =F$25-F$54 -> 93912801 | G55: =G$25-G$54 -> 66117926 | H55: =H$25-H$54 -> 41800681 | I55: =I$25-I$54 -> 67471038 | J55: =J$25-J$54 -> 48716627 | ... M55: =M$25-M$54 -> 87633229
A56: VAN après impôts | C56: =NPV($B$11,C55:M55) -> 1.4052529e+08
A57: TEMI | C57: =1-(C$56/C$26) -> 0.60766343
A58: TRI après impôts | C58: =IRR(C55:M55) -> 0.15060915 | F58: =IRR($C$55:F55) -> -0.274356 | G58: =IRR($C$55:G55) -> -0.1096526 | H58: =IRR($C$55:H55) -> -0.037981949 | I58: =IRR($C$55:I55) -> 0.039866811 | J58: =IRR($C$55:J55) -> 0.077305814 | K58: =IRR($C$55:K55) -> 0.10075814 | L58: =IRR($C$55:L55) -> 0.12587439 | M58: =IRR($C$55:M55) -> 0.15060915
A59: Part de la société | C59: =1-C57 -> 0.39233657

Sheet Code général des impôts 2017
A1: Projet aurifère_De Houndé | B1: Unités | C1: ='Modèle de base (CM 2003)'!C1 -> 2011 | D1: ='Modèle de base (CM 2003)'!D1 -> 2012 | E1: ='Modèle de base (CM 2003)'!E1 -> 2013 | F1: ='Modèle de base (CM 2003)'!F1 -> 2014 | G1: ='Modèle de base (CM 2003)'!G1 -> 2015 | H1: ='Modèle de base (CM 2003)'!H1 -> 2016 | I1: ='Modèle de base (CM 2003)'!I1 -> 2017 | J1: ='Modèle de base (CM 2003)'!J1 -> 2018 | ... M1: ='Modèle de base (CM 2003)'!M1 -> 2021
C2: ='Modèle de base (CM 2003)'!C2 -> 0 | D2: ='Modèle de base (CM 2003)'!D2 -> 0 | E2: ='Modèle de base (CM 2003)'!E2 -> 0 | F2: ='Modèle de base (CM 2003)'!F2 -> 0 | G2: ='Modèle de base (CM 2003)'!G2 -> 0 | H2: ='Modèle de base (CM 2003)'!H2 -> 0 | I2: ='Modèle de base (CM 2003)'!I2 -> 0 | J2: ='Modèle de base (CM 2003)'!J2 -> 0 | ... M2: ='Modèle de base (CM 2003)'!M2 -> 0
C3: ='Modèle de base (CM 2003)'!C3 -> 0 | D3: ='Modèle de base (CM 2003)'!D3 -> 0 | E3: ='Modèle de base (CM 2003)'!E3 -> 0 | F3: ='Modèle de base (CM 2003)'!F3 -> 0 | G3: ='Modèle de base (CM 2003)'!G3 -> 0 | H3: ='Modèle de base (CM 2003)'!H3 -> 0 | I3: ='Modèle de base (CM 2003)'!I3 -> 0 | J3: ='Modèle de base (CM 2003)'!J3 -> 0 | ... M3: ='Modèle de base (CM 2003)'!M3 -> 0
A4: Production | C4: ='Modèle de base (CM 2003)'!C4 -> 0 | D4: ='Modèle de base (CM 2003)'!D4 -> 0 | E4: ='Modèle de base (CM 2003)'!E4 -> 0 | F4: ='Modèle de base (CM 2003)'!F4 -> 0 | G4: ='Modèle de base (CM 2003)'!G4 -> 0 | H4: ='Modèle de base (CM 2003)'!H4 -> 0 | I4: ='Modèle de base (CM 2003)'!I4 -> 0 | J4: ='Modèle de base (CM 2003)'!J4 -> 0 | ... M4: ='Modèle de base (CM 2003)'!M4 -> 0 | Q4: Données | R4: VAN AV IMPÔT | S4: VAN AP IMPÔT | T4: TEMI | U4: TRI AV | V4: TRI AP
A5: Quantité Traité | B5: t | C5: ='Modèle de base (CM 2003)'!C5 -> 0 | D5: ='Modèle de base (CM 2003)'!D5 -> 0 | E5: ='Modèle de base (CM 2003)'!E5 -> 0 | F5: ='Modèle de base (CM 2003)'!F5 -> 0 | G5: ='Modèle de base (CM 2003)'!G5 -> 0 | H5: ='Modèle de base (CM 2003)'!H5 -> 0 | I5: ='Modèle de base (CM 2003)'!I5 -> 0 | J5: ='Modèle de base (CM 2003)'!J5 -> 0 | ... M5: ='Modèle de base (CM 2003)'!M5 -> 0 | P5: Cours de l'or | Q5: 1300 | R5: =C26 -> 3.5817536e+08 | S5: =C56 -> 99393777 | T5: =C57 -> 0.72249968 | U5: =C27 -> 0.27738179 | V5: =C58 -> 0.12307964
A6: Teneur en or | B6: g/t | C6: ='Modèle de base (CM 2003)'!C6 -> 0 | D6: ='Modèle de base (CM 2003)'!D6 -> 0 | E6: ='Modèle de base (CM 2003)'!E6 -> 0 | F6: ='Modèle de base (CM 2003)'!F6 -> 0 | G6: ='Modèle de base (CM 2003)'!G6 -> 0 | H6: ='Modèle de base (CM 2003)'!H6 -> 0 | I6: ='Modèle de base (CM 2003)'!I6 -> 0 | J6: ='Modèle de base (CM 2003)'!J6 -> 0 | ... M6: ='Modèle de base (CM 2003)'!M6 -> 0 | P6: Taux d'actualisation | Q6: 0.05
A7: Quantité d'Or Récupéré | B7: oz | C7: ='Modèle de base (CM 2003)'!C7 -> 0 | D7: ='Modèle de base (CM 2003)'!D7 -> 0 | E7: ='Modèle de base (CM 2003)'!E7 -> 191176 | F7: ='Modèle de base (CM 2003)'!F7 -> 215238 | G7: ='Modèle de base (CM 2003)'!G7 -> 189807 | H7: ='Modèle de base (CM 2003)'!H7 -> 168325 | I7: ='Modèle de base (CM 2003)'!I7 -> 210971 | J7: ='Modèle de base (CM 2003)'!J7 -> 167700 | ... M7: ='Modèle de base (CM 2003)'!M7 -> 119370 | P7: IS | Q7: 0.275
A8: Cours de l'or | B8: =Q5 -> 1300 | C8: ='Modèle de base (CM 2003)'!C8 -> 0 | D8: ='Modèle de base (CM 2003)'!D8 -> 0 | E8: ='Modèle de base (CM 2003)'!E8 -> 1300 | F8: ='Modèle de base (CM 2003)'!F8 -> 1300 | G8: ='Modèle de base (CM 2003)'!G8 -> 1300 | H8: ='Modèle de base (CM 2003)'!H8 -> 1300 | I8: ='Modèle de base (CM 2003)'!I8 -> 1300 | J8: ='Modèle de base (CM 2003)'!J8 -> 1300 | ... M8: ='Modèle de base (CM 2003)'!M8 -> 1300 | P8: Taux de redevance propotionelle | Q8: 0.04
A9: Chiffre d'Affaire | B9: $ | C9: =$B$8*C7 -> 0 | D9: =$B$8*D7 -> 0 | E9: =$B$8*E7 -> 248528800 | F9: =$B$8*F7 -> 279809400 | G9: =$B$8*G7 -> 246749100 | H9: =$B$8*H7 -> 218822500 | I9: =$B$8*I7 -> 274262300 | J9: =$B$8*J7 -> 218010000 | ... M9: =$B$8*M7 -> 155181000
A10: Taux de change | B10: 0.00177 | C10: ='Modèle de base (CM 2003)'!C10 -> 0 | D10: ='Modèle de base (CM 2003)'!D10 -> 0 | E10: ='Modèle de base (CM 2003)'!E10 -> 0 | F10: ='Modèle de base (CM 2003)'!F10 -> 0 | G10: ='Modèle de base (CM 2003)'!G10 -> 0 | H10: ='Modèle de base (CM 2003)'!H10 -> 0 | I10: ='Modèle de base (CM 2003)'!I10 -> 0 | J10: ='Modèle de base (CM 2003)'!J10 -> 0 | ... M10: ='Modèle de base (CM 2003)'!M10 -> 0
A11: Taux d'actualisation | B11: =Q6 -> 0.05 | C11: ='Modèle de base (CM 2003)'!C11 -> 0 | D11: ='Modèle de base (CM 2003)'!D11 -> 0 | E11: ='Modèle de base (CM 2003)'!E11 -> 0 | F11: ='Modèle de base (CM 2003)'!F11 -> 0 | G11: ='Modèle de base (CM 2003)'!G11 -> 0 | H11: ='Modèle de base (CM 2003)'!H11 -> 0 | I11: ='Modèle de base (CM 2003)'!I11 -> 0 | J11: ='Modèle de base (CM 2003)'!J11 -> 0 | ... M11: ='Modèle de base (CM 2003)'!M11 -> 0
C12: ='Modèle de base (CM 2003)'!C12 -> 0 | D12: ='Modèle de base (CM 2003)'!D12 -> 0 | E12: ='Modèle de base (CM 2003)'!E12 -> 0 | F12: ='Modèle de base (CM 2003)'!F12 -> 0 | G12: ='Modèle de base (CM 2003)'!G12 -> 0 | H12: ='Modèle de base (CM 2003)'!H12 -> 0 | I12: ='Modèle de base (CM 2003)'!I12 -> 0 | J12: ='Modèle de base (CM 2003)'!J12 -> 0 | ... M12: ='Modèle de base (CM 2003)'!M12 -> 0
A13: Coûts d'investissement (CAPEX) | C13: ='Modèle de base (CM 2003)'!C13 -> 0 | D13: ='Modèle de base (CM 2003)'!D13 -> 0 | E13: ='Modèle de base (CM 2003)'!E13 -> 0 | F13: ='Modèle de base (CM 2003)'!F13 -> 0 | G13: ='Modèle de base (CM 2003)'!G13 -> 0 | H13: ='Modèle de base (CM 2003)'!H13 -> 0 | I13: ='Modèle de base (CM 2003)'!I13 -> 0 | J13: ='Modèle de base (CM 2003)'!J13 -> 0 | ... M13: ='Modèle de base (CM 2003)'!M13 -> 0
A14: Coûts des construction industrielles | B14: $ | C14: ='Modèle de base (CM 2003)'!C14 -> 49760265 | D14: ='Modèle de base (CM 2003)'!D14 -> 116107284 | E14: ='Modèle de base (CM 2003)'!E14 -> 0 | F14: ='Modèle de base (CM 2003)'!F14 -> 0 | G14: ='Modèle de base (CM 2003)'!G14 -> 0 | H14: ='Modèle de base (CM 2003)'!H14 -> 0 | I14: ='Modèle de base (CM 2003)'!I14 -> 0 | J14: ='Modèle de base (CM 2003)'!J14 -> 0 | ... M14: ='Modèle de base (CM 2003)'!M14 -> 0
A15: Coûts des biens d'équipement | C15: ='Modèle de base (CM 2003)'!C15 -> 23685527 | D15: ='Modèle de base (CM 2003)'!D15 -> 125300533 | E15: ='Modèle de base (CM 2003)'!E15 -> 11632917 | F15: ='Modèle de base (CM 2003)'!F15 -> 3722927 | G15: ='Modèle de base (CM 2003)'!G15 -> 18272647 | H15: ='Modèle de base (CM 2003)'!H15 -> 4482500 | I15: ='Modèle de base (CM 2003)'!I15 -> 2137128 | J15: ='Modèle de base (CM 2003)'!J15 -> 1103055 | ... M15: ='Modèle de base (CM 2003)'!M15 -> 542926
A16: Autres depenses | B16: $ | C16: ='Modèle de base (CM 2003)'!C16 -> 0 | D16: ='Modèle de base (CM 2003)'!D16 -> 0 | E16: ='Modèle de base (CM 2003)'!E16 -> 1595000 | F16: ='Modèle de base (CM 2003)'!F16 -> 2708200 | G16: ='Modèle de base (CM 2003)'!G16 -> 249700 | H16: ='Modèle de base (CM 2003)'!H16 -> 2581553 | I16: ='Modèle de base (CM 2003)'!I16 -> 469553 | J16: ='Modèle de base (CM 2003)'!J16 -> 3654542 | ... M16: ='Modèle de base (CM 2003)'!M16 -> 0
A17: Coûts de réhabilitation du site | B17: $ | C17: ='Modèle de base (CM 2003)'!C17 -> 0 | D17: ='Modèle de base (CM 2003)'!D17 -> 0 | E17: ='Modèle de base (CM 2003)'!E17 -> 2830244 | F17: ='Modèle de base (CM 2003)'!F17 -> 3314368 | G17: ='Modèle de base (CM 2003)'!G17 -> 3215137 | H17: ='Modèle de base (CM 2003)'!H17 -> 3842412 | I17: ='Modèle de base (CM 2003)'!I17 -> 4018506 | J17: ='Modèle de base (CM 2003)'!J17 -> 2935298 | ... M17: ='Modèle de base (CM 2003)'!M17 -> 3165512
A18: TOTAL CAPITAL | B18: $ | C18: ='Modèle de base (CM 2003)'!C18 -> 73445792 | D18: ='Modèle de base (CM 2003)'!D18 -> 241407817 | E18: ='Modèle de base (CM 2003)'!E18 -> 16058161 | F18: ='Modèle de base (CM 2003)'!F18 -> 9745495 | G18: ='Modèle de base (CM 2003)'!G18 -> 21737484 | H18: ='Modèle de base (CM 2003)'!H18 -> 10906465 | I18: ='Modèle de base (CM 2003)'!I18 -> 6625187 | J18: ='Modèle de base (CM 2003)'!J18 -> 7692895 | ... M18: ='Modèle de base (CM 2003)'!M18 -> 3708438
C19: ='Modèle de base (CM 2003)'!C19 -> 0 | D19: ='Modèle de base (CM 2003)'!D19 -> 0 | E19: ='Modèle de base (CM 2003)'!E19 -> 0 | F19: ='Modèle de base (CM 2003)'!F19 -> 0 | G19: ='Modèle de base (CM 2003)'!G19 -> 0 | H19: ='Modèle de base (CM 2003)'!H19 -> 0 | I19: ='Modèle de base (CM 2003)'!I19 -> 0 | J19: ='Modèle de base (CM 2003)'!J19 -> 0 | ... M19: ='Modèle de base (CM 2003)'!M19 -> 0
A20: Coûts d'exploitation (Opex)/hors redevance | B20: $ | C20: ='Modèle de base (CM 2003)'!C20 -> 0 | D20: ='Modèle de base (CM 2003)'!D20 -> 0 | E20: ='Modèle de base (CM 2003)'!E20 -> 115668594 | F20: ='Modèle de base (CM 2003)'!F20 -> 128519703 | G20: ='Modèle de base (CM 2003)'!G20 -> 131246978 | H20: ='Modèle de base (CM 2003)'!H20 -> 152348402 | I20: ='Modèle de base (CM 2003)'!I20 -> 157632470 | J20: ='Modèle de base (CM 2003)'!J20 -> 132358509 | ... M20: ='Modèle de base (CM 2003)'!M20 -> 9542514
A21: Coûts d'exploitation moyen (Opex) /hors redevance | B21: $/oz | C21: ='Modèle de base (CM 2003)'!C21 -> 0 | D21: ='Modèle de base (CM 2003)'!D21 -> 0 | E21: ='Modèle de base (CM 2003)'!E21 -> 605.03721 | F21: ='Modèle de base (CM 2003)'!F21 -> 597.10508 | G21: ='Modèle de base (CM 2003)'!G21 -> 691.47596 | H21: ='Modèle de base (CM 2003)'!H21 -> 905.08482 | I21: ='Modèle de base (CM 2003)'!I21 -> 747.17601 | J21: ='Modèle de base (CM 2003)'!J21 -> 789.25766 | ... M21: ='Modèle de base (CM 2003)'!M21 -> 79.940638
C22: ='Modèle de base (CM 2003)'!C22 -> 0 | D22: ='Modèle de base (CM 2003)'!D22 -> 0 | E22: ='Modèle de base (CM 2003)'!E22 -> 0 | F22: ='Modèle de base (CM 2003)'!F22 -> 0 | G22: ='Modèle de base (CM 2003)'!G22 -> 0 | H22: ='Modèle de base (CM 2003)'!H22 -> 0 | I22: ='Modèle de base (CM 2003)'!I22 -> 0 | J22: ='Modèle de base (CM 2003)'!J22 -> 0 | ... M22: ='Modèle de base (CM 2003)'!M22 -> 0
A23: Coût Totaux | C23: =C$18+C$20 -> 73445792 | D23: =D$18+D$20 -> 241407817 | E23: =E$18+E$20 -> 131726755 | F23: =F$18+F$20 -> 138265198 | G23: =G$18+G$20 -> 152984462 | H23: =H$18+H$20 -> 163254867 | I23: =I$18+I$20 -> 164257657 | J23: =J$18+J$20 -> 140051404 | ... M23: =M$18+M$20 -> 13250952
C24: ='Modèle de base (CM 2003)'!C24 -> 0 | D24: ='Modèle de base (CM 2003)'!D24 -> 0 | E24: ='Modèle de base (CM 2003)'!E24 -> 0 | F24: ='Modèle de base (CM 2003)'!F24 -> 0 | G24: ='Modèle de base (CM 2003)'!G24 -> 0 | H24: ='Modèle de base (CM 2003)'!H24 -> 0 | I24: ='Modèle de base (CM 2003)'!I24 -> 0 | J24: ='Modèle de base (CM 2003)'!J24 -> 0 | ... M24: ='Modèle de base (CM 2003)'!M24 -> 0
A25: Cash-flows avant impôts | C25: =C$9-C$23 -> -73445792 | D25: =D$9-D$23 -> -241407817 | E25: =E$9-E$23 -> 116802045 | F25: =F$9-F$23 -> 141544202 | G25: =G$9-G$23 -> 93764638 | H25: =H$9-H$23 -> 55567633 | I25: =I$9-I$23 -> 110004643 | J25: =J$9-J$23 -> 77958596 | ... M25: =M$9-M$23 -> 141930048
A26: VAN avant impôts | C26: =NPV($B$11,C25:M25) -> 3.5817536e+08 | D26: ='Modèle de base (CM 2003)'!D26 -> 0 | E26: ='Modèle de base (CM 2003)'!E26 -> 0 | F26: ='Modèle de base (CM 2003)'!F26 -> 0 | G26: ='Modèle de base (CM 2003)'!G26 -> 0 | H26: ='Modèle de base (CM 2003)'!H26 -> 0 | I26: ='Modèle de base (CM 2003)'!I26 -> 0 | J26: ='Modèle de base (CM 2003)'!J26 -> 0 | K26: ='Modèle de base (CM 2003)'!K26 -> 0 | ... M26: ='Modèle de base (CM 2003)'!M26 -> 0
A27: TRI avant impôts | C27: =IRR(C25:M25) -> 0.27738179 | D27: ='Modèle de base (CM 2003)'!D27 -> 0 | E27: ='Modèle de base (CM 2003)'!E27 -> -0.3913088 | F27: ='Modèle de base (CM 2003)'!F27 -> 0.11243079 | G27: ='Modèle de base (CM 2003)'!G27 -> 0.2768997 | H27: ='Modèle de base (CM 2003)'!H27 -> 0.3407976 | I27: ='Modèle de base (CM 2003)'!I27 -> 0.40012659 | J27: ='Modèle de base (CM 2003)'!J27 -> 0.42540794 | K27: ='Modèle de base (CM 2003)'!K27 -> 0.43824983 | ... M27: ='Modèle de base (CM 2003)'!M27 -> 0.45818507
C28: ='Modèle de base (CM 2003)'!C28 -> 0 | D28: ='Modèle de base (CM 2003)'!D28 -> 0 | E28: ='Modèle de base (CM 2003)'!E28 -> 0 | F28: ='Modèle de base (CM 2003)'!F28 -> 0 | G28: ='Modèle de base (CM 2003)'!G28 -> 0 | H28: ='Modèle de base (CM 2003)'!H28 -> 0 | I28: ='Modèle de base (CM 2003)'!I28 -> 0 | J28: ='Modèle de base (CM 2003)'!J28 -> 0 | ... M28: ='Modèle de base (CM 2003)'!M28 -> 0
A29: Droits fixes | C29: =B10*'Données fiscales'!C110 -> 9735 | D29: ='Modèle de base (CM 2003)'!D29 -> 0 | E29: ='Modèle de base (CM 2003)'!E29 -> 0 | F29: ='Modèle de base (CM 2003)'!F29 -> 0 | G29: ='Modèle de base (CM 2003)'!G29 -> 0 | H29: ='Modèle de base (CM 2003)'!H29 -> 0 | I29: ='Modèle de base (CM 2003)'!I29 -> 0 | J29: ='Modèle de base (CM 2003)'!J29 -> 0 | K29: ='Modèle de base (CM 2003)'!K29 -> 0 | ... M29: ='Modèle de base (CM 2003)'!M29 -> 0
C30: ='Modèle de base (CM 2003)'!C30 -> 0 | D30: ='Modèle de base (CM 2003)'!D30 -> 0 | E30: ='Modèle de base (CM 2003)'!E30 -> 0 | F30: ='Modèle de base (CM 2003)'!F30 -> 0 | G30: ='Modèle de base (CM 2003)'!G30 -> 0 | H30: ='Modèle de base (CM 2003)'!H30 -> 0 | I30: ='Modèle de base (CM 2003)'!I30 -> 0 | J30: ='Modèle de base (CM 2003)'!J30 -> 0 | ... M30: ='Modèle de base (CM 2003)'!M30 -> 0
C31: ='Modèle de base (CM 2003)'!C31 -> 0 | D31: ='Modèle de base (CM 2003)'!D31 -> 0 | E31: ='Modèle de base (CM 2003)'!E31 -> 0 | F31: ='Modèle de base (CM 2003)'!F31 -> 0 | G31: ='Modèle de base (CM 2003)'!G31 -> 0 | H31: ='Modèle de base (CM 2003)'!H31 -> 0 | I31: ='Modèle de base (CM 2003)'!I31 -> 0 | J31: ='Modèle de base (CM 2003)'!J31 -> 0 | ... M31: ='Modèle de base (CM 2003)'!M31 -> 0
A32: Superficie de la mine | C32: ='Modèle de base (CM 2003)'!C32 -> 23.2 | D32: ='Modèle de base (CM 2003)'!D32 -> 23.2 | E32: ='Modèle de base (CM 2003)'!E32 -> 23.2 | F32: ='Modèle de base (CM 2003)'!F32 -> 23.2 | G32: ='Modèle de base (CM 2003)'!G32 -> 23.2 | H32: ='Modèle de base (CM 2003)'!H32 -> 23.2 | I32: ='Modèle de base (CM 2003)'!I32 -> 23.2 | J32: ='Modèle de base (CM 2003)'!J32 -> 23.2 | ... M32: ='Modèle de base (CM 2003)'!M32 -> 23.2
A33: Redevance superficière | C33: =$B$10*C32*'Données fiscales'!C90 -> 25665 | D33: =$B$10*D32*'Données fiscales'!D90 -> 307980 | E33: =$B$10*E32*'Données fiscales'!E90 -> 307980 | F33: =$B$10*F32*'Données fiscales'!F90 -> 307980 | G33: =$B$10*G32*'Données fiscales'!G90 -> 307980 | H33: =$B$10*H32*'Données fiscales'!H90 -> 410640 | I33: =$B$10*I32*'Données fiscales'!I90 -> 410640 | J33: =$B$10*J32*'Données fiscales'!J90 -> 410640 | ... M33: =$B$10*M32*'Données fiscales'!M90 -> 615960
C34: ='Modèle de base (CM 2003)'!C34 -> 0 | D34: ='Modèle de base (CM 2003)'!D34 -> 0 | E34: ='Modèle de base (CM 2003)'!E34 -> 0 | F34: ='Modèle de base (CM 2003)'!F34 -> 0 | G34: ='Modèle de base (CM 2003)'!G34 -> 0 | H34: ='Modèle de base (CM 2003)'!H34 -> 0 | I34: ='Modèle de base (CM 2003)'!I34 -> 0 | J34: ='Modèle de base (CM 2003)'!J34 -> 0 | ... M34: ='Modèle de base (CM 2003)'!M34 -> 0
A35: Redevance proportionnelle | C35: ='Modèle de base (CM 2003)'!C35 -> 0 | D35: ='Modèle de base (CM 2003)'!D35 -> 0 | E35: ='Modèle de base (CM 2003)'!E35 -> 0 | F35: ='Modèle de base (CM 2003)'!F35 -> 0 | G35: ='Modèle de base (CM 2003)'!G35 -> 0 | H35: ='Modèle de base (CM 2003)'!H35 -> 0 | I35: ='Modèle de base (CM 2003)'!I35 -> 0 | J35: ='Modèle de base (CM 2003)'!J35 -> 0 | ... M35: ='Modèle de base (CM 2003)'!M35 -> 0
A36: taux de la redevance | B36: =Q8 -> 0.04 | C36: ='Modèle de base (CM 2003)'!C36 -> 0 | D36: ='Modèle de base (CM 2003)'!D36 -> 0 | E36: ='Modèle de base (CM 2003)'!E36 -> 0.04 | F36: ='Modèle de base (CM 2003)'!F36 -> 0.04 | G36: ='Modèle de base (CM 2003)'!G36 -> 0.04 | H36: ='Modèle de base (CM 2003)'!H36 -> 0.04 | I36: ='Modèle de base (CM 2003)'!I36 -> 0.04 | J36: ='Modèle de base (CM 2003)'!J36 -> 0.04 | ... M36: ='Modèle de base (CM 2003)'!M36 -> 0.04
A37: Montant de la redevance | C37: =$B$36*C9 -> 0 | D37: =$B$36*D9 -> 0 | E37: =$B$36*E9 -> 9941152 | F37: =$B$36*F9 -> 11192376 | G37: =$B$36*G9 -> 9869964 | H37: =$B$36*H9 -> 8752900 | I37: =$B$36*I9 -> 10970492 | J37: =$B$36*J9 -> 8720400 | ... M37: =$B$36*M9 -> 6207240
C38: ='Modèle de base (CM 2003)'!C38 -> 0 | D38: ='Modèle de base (CM 2003)'!D38 -> 0 | E38: ='Modèle de base (CM 2003)'!E38 -> 0 | F38: ='Modèle de base (CM 2003)'!F38 -> 0 | G38: ='Modèle de base (CM 2003)'!G38 -> 0 | H38: ='Modèle de base (CM 2003)'!H38 -> 0 | I38: ='Modèle de base (CM 2003)'!I38 -> 0 | J38: ='Modèle de base (CM 2003)'!J38 -> 0 | ... M38: ='Modèle de base (CM 2003)'!M38 -> 0
A39: Charges d'amortissement | C39: ='Modèle de base (CM 2003)'!C39 -> 14450237 | D39: ='Modèle de base (CM 2003)'!D39 -> 72391495 | E39: ='Modèle de base (CM 2003)'!E39 -> 54722766 | F39: ='Modèle de base (CM 2003)'!F39 -> 41469139 | G39: ='Modèle de base (CM 2003)'!G39 -> 42554951 | H39: ='Modèle de base (CM 2003)'!H39 -> 38090104 | I39: ='Modèle de base (CM 2003)'!I39 -> 22807098 | J39: ='Modèle de base (CM 2003)'!J39 -> 20561890 | ... M39: ='Modèle de base (CM 2003)'!M39 -> 15427244
A40: ='Code Minier 2015'!A40 -> Developpement local | B40: ='Code Minier 2015'!B40 -> 0 | C40: ='Code Minier 2015'!C40 -> 0 | D40: ='Code Minier 2015'!D40 -> 0 | E40: ='Code Minier 2015'!E40 -> 2485288 | F40: ='Code Minier 2015'!F40 -> 2798094 | G40: ='Code Minier 2015'!G40 -> 2467491 | H40: ='Code Minier 2015'!H40 -> 2188225 | ... M40: ='Code Minier 2015'!M40 -> 1551810
A42: Bénéfice imposable | C42: =C9-(C$23+C$29+C$33+C$37+C$39+C$40) -> -87931429 | D42: =D9-(D$23+D$29+D$33+D$37+D$39) -> -3.1410729e+08 | E42: =E9-(E$23+E$29+E$33+E$37+E$39) -> 51830147 | F42: =F9-(F$23+F$29+F$33+F$37+F$39) -> 88574707 | G42: =G9-(G$23+G$29+G$33+G$37+G$39) -> 41031743 | H42: =H9-(H$23+H$29+H$33+H$37+H$39) -> 8313988.7 | I42: =I9-(I$23+I$29+I$33+I$37+I$39) -> 75816413 | J42: =J9-(J$23+J$29+J$33+J$37+J$39) -> 48265666 | K42: =K9-(K$23+K$29+K$33+K$37+K$39) -> 34453588 | ... M42: =M9-(M$23+M$29+M$33+M$37+M$39) -> 1.196796e+08
A43: Taux IS | B43: =Q7 -> 0.275 | C43: ='Modèle de base (CM 2003)'!C42 -> 0 | D43: ='Modèle de base (CM 2003)'!D42 -> 0 | E43: 27;5% | F43: 27;5% | G43: 27;5% | H43: 27;5% | I43: 27;5% | J43: 27;5% | K43: 27;5% | L43: 27;5% | M43: 27;5%
A44: Montant IMF | C44: ='Modèle de base (CM 2003)'!C43 -> 0 | D44: ='Modèle de base (CM 2003)'!D43 -> 0 | E44: ='Modèle de base (CM 2003)'!E43 -> 0 | F44: ='Modèle de base (CM 2003)'!F43 -> 0 | G44: ='Modèle de base (CM 2003)'!G43 -> 0 | H44: ='Modèle de base (CM 2003)'!H43 -> 0 | I44: ='Modèle de base (CM 2003)'!I43 -> 0 | J44: ='Modèle de base (CM 2003)'!J43 -> 1341600 | ... M44: ='Modèle de base (CM 2003)'!M43 -> 954960
A45: IS/IMF | C45: =IF(C$42*$B$43>0,C$42*$B$43,C$44) -> 0 | D45: =IF(D$42*$B$43>0,D$42*$B$43,D$44) -> 0 | E45: =IF(E$42*$B$43>0,E$42*$B$43,E$44) -> 14253291 | F45: =IF(F$42*$B$43>0,F$42*$B$43,F$44) -> 24358044 | G45: =IF(G$42*$B$43>0,G$42*$B$43,G$44) -> 11283729 | H45: =IF(H$42*$B$43>0,H$42*$B$43,H$44) -> 2286346.9 | I45: =IF(I$42*$B$43>0,I$42*$B$43,I$44) -> 20849513 | J45: =IF(J$42*$B$43>0,J$42*$B$43,J$44) -> 13273058 | ... M45: =IF(M$42*$B$43>0,M$42*$B$43,M$44) -> 32911891
C46: ='Modèle de base (CM 2003)'!C45 -> 0 | D46: ='Modèle de base (CM 2003)'!D45 -> 0 | E46: ='Modèle de base (CM 2003)'!E45 -> 0 | F46: ='Modèle de base (CM 2003)'!F45 -> 0 | G46: ='Modèle de base (CM 2003)'!G45 -> 0 | H46: ='Modèle de base (CM 2003)'!H45 -> 0 | I46: ='Modèle de base (CM 2003)'!I45 -> 0 | J46: ='Modèle de base (CM 2003)'!J45 -> 0 | ... M46: ='Modèle de base (CM 2003)'!M45 -> 0
A47: Résultat après impôt | C47: =C$42-C$45 -> -87931429 | D47: =D$42-D$45 -> -3.1410729e+08 | E47: =E$42-E$45 -> 37576857 | F47: =F$42-F$45 -> 64216662 | G47: =G$42-G$45 -> 29748014 | H47: =H$42-H$45 -> 6027641.8 | I47: =I$42-I$45 -> 54966899 | J47: =J$42-J$45 -> 34992608 | ... M47: =M$42-M$45 -> 86767713 | N47: =N42-N45 -> 0
A48: Participation de l'Etat | B48: 0.1 | C48: ='Modèle de base (CM 2003)'!C47 -> 0 | D48: ='Modèle de base (CM 2003)'!D47 -> 0 | E48: ='Modèle de base (CM 2003)'!E47 -> 0 | F48: ='Modèle de base (CM 2003)'!F47 -> 0 | G48: ='Modèle de base (CM 2003)'!G47 -> 0 | H48: ='Modèle de base (CM 2003)'!H47 -> 0 | I48: ='Modèle de base (CM 2003)'!I47 -> 0 | J48: ='Modèle de base (CM 2003)'!J47 -> 0 | ... M48: ='Modèle de base (CM 2003)'!M47 -> 0
A49: Dividende de l'Etat | C49: =IF(C47>0,C47*$B$48,0) -> 0 | D49: =IF(D47>0,D47*$B$48,0) -> 0 | E49: =IF(E47>0,E47*$B$48,0) -> 3757685.7 | F49: =IF(F47>0,F47*$B$48,0) -> 6421666.2 | G49: =IF(G47>0,G47*$B$48,0) -> 2974801.4 | H49: =IF(H47>0,H47*$B$48,0) -> 602764.18 | I49: =IF(I47>0,I47*$B$48,0) -> 5496689.9 | J49: =IF(J47>0,J47*$B$48,0) -> 3499260.8 | ... M49: =IF(M47>0,M47*$B$48,0) -> 8676771.3
A50: Part de la société | C50: =C$47-C$49 -> -87931429 | D50: ='Modèle de base (CM 2003)'!D49 -> -3.1415225e+08 | E50: ='Modèle de base (CM 2003)'!E49 -> 62503669 | F50: ='Modèle de base (CM 2003)'!F49 -> 88053202 | G50: ='Modèle de base (CM 2003)'!G49 -> 55955953 | H50: ='Modèle de base (CM 2003)'!H49 -> 33188013 | I50: ='Modèle de base (CM 2003)'!I49 -> 79861929 | J50: ='Modèle de base (CM 2003)'!J49 -> 56454445 | K50: ='Modèle de base (CM 2003)'!K49 -> 43168178 | ... M50: ='Modèle de base (CM 2003)'!M49 -> 90071426
A51: Impôt sur les dividendes | C51: =IF(C$50>0,C$50*'Données fiscales'!C105,0) -> 0 | D51: =IF(D$50>0,D$50*'Données fiscales'!D105,0) -> 0 | E51: =IF(E$50>0,E$50*'Données fiscales'!E105,0) -> 7812958.6 | F51: =IF(F$50>0,F$50*'Données fiscales'!F105,0) -> 11006650 | G51: =IF(G$50>0,G$50*'Données fiscales'!G105,0) -> 6994494.2 | H51: =IF(H$50>0,H$50*'Données fiscales'!H105,0) -> 4148501.6 | I51: =IF(I$50>0,I$50*'Données fiscales'!I105,0) -> 9982741.1 | J51: =IF(J$50>0,J$50*'Données fiscales'!J105,0) -> 7056805.6 | ... M51: =IF(M$50>0,M$50*'Données fiscales'!M105,0) -> 11258928
C52: ='Modèle de base (CM 2003)'!C51 -> 0 | D52: ='Modèle de base (CM 2003)'!D51 -> 0 | E52: ='Modèle de base (CM 2003)'!E51 -> 0 | F52: ='Modèle de base (CM 2003)'!F51 -> 0 | G52: ='Modèle de base (CM 2003)'!G51 -> 0 | H52: ='Modèle de base (CM 2003)'!H51 -> 0 | I52: ='Modèle de base (CM 2003)'!I51 -> 0 | J52: ='Modèle de base (CM 2003)'!J51 -> 0 | ... M52: ='Modèle de base (CM 2003)'!M51 -> 0
C53: ='Modèle de base (CM 2003)'!C52 -> 0 | D53: ='Modèle de base (CM 2003)'!D52 -> 0 | E53: ='Modèle de base (CM 2003)'!E52 -> 0 | F53: ='Modèle de base (CM 2003)'!F52 -> 0 | G53: ='Modèle de base (CM 2003)'!G52 -> 0 | H53: ='Modèle de base (CM 2003)'!H52 -> 0 | I53: ='Modèle de base (CM 2003)'!I52 -> 0 | J53: ='Modèle de base (CM 2003)'!J52 -> 0 | ... M53: ='Modèle de base (CM 2003)'!M52 -> 0
A54: Recettes totales de l'Etat | C54: =C$29+C$33+C$37+C$45+C$49+C$51+C$40 -> 35400 | D54: =D$29+D$33+D$37+D$45+D$49+D$51+D$40 -> 307980 | E54: =E$29+E$33+E$37+E$45+E$49+E$51+E$40 -> 38558355 | F54: =F$29+F$33+F$37+F$45+F$49+F$51+F$40 -> 56084811 | G54: =G$29+G$33+G$37+G$45+G$49+G$51+G$40 -> 33898460 | H54: =H$29+H$33+H$37+H$45+H$49+H$51+H$40 -> 18389378 | I54: =I$29+I$33+I$37+I$45+I$49+I$51+I$40 -> 50452700 | J54: =J$29+J$33+J$37+J$45+J$49+J$51+J$40 -> 35140265 | ... M54: =M$29+M$33+M$37+M$45+M$49+M$51+M$40 -> 61222601
A55: Cash-Flows après imôts | C55: =C$25-C$54 -> -73481192 | D55: =D$25-D$54 -> -241715797 | E55: =E$25-E$54 -> 78243690 | F55: =F$25-F$54 -> 85459391 | G55: =G$25-G$54 -> 59866178 | H55: =H$25-H$54 -> 37178255 | I55: =I$25-I$54 -> 59551943 | J55: =J$25-J$54 -> 42818331 | ... M55: =M$25-M$54 -> 80707447
A56: VAN après impôts | C56: =NPV($B$11,C55:M55) -> 99393777 | D56: ='Modèle de base (CM 2003)'!D55 -> 0 | E56: ='Modèle de base (CM 2003)'!E55 -> 0 | F56: ='Modèle de base (CM 2003)'!F55 -> 0 | G56: ='Modèle de base (CM 2003)'!G55 -> 0 | H56: ='Modèle de base (CM 2003)'!H55 -> 0 | I56: ='Modèle de base (CM 2003)'!I55 -> 0 | J56: ='Modèle de base (CM 2003)'!J55 -> 0 | K56: ='Modèle de base (CM 2003)'!K55 -> 0 | ... M56: ='Modèle de base (CM 2003)'!M55 -> 0
A57: TEMI | C57: =1-(C56/C26) -> 0.72249968 | D57: ='Modèle de base (CM 2003)'!D56 -> 0 | E57: ='Modèle de base (CM 2003)'!E56 -> 0 | F57: ='Modèle de base (CM 2003)'!F56 -> 0 | G57: ='Modèle de base (CM 2003)'!G56 -> 0 | H57: ='Modèle de base (CM 2003)'!H56 -> 0 | I57: ='Modèle de base (CM 2003)'!I56 -> 0 | J57: ='Modèle de base (CM 2003)'!J56 -> 0 | K57: ='Modèle de base (CM 2003)'!K56 -> 0 | ... M57: ='Modèle de base (CM 2003)'!M56 -> 0
A58: TRI après impôts | C58: =IRR(C55:M55) -> 0.12307964 | D58: ='Modèle de base (CM 2003)'!D57 -> 0 | E58: ='Modèle de base (CM 2003)'!E57 -> 0 | F58: ='Modèle de base (CM 2003)'!F57 -> -0.1492555 | G58: ='Modèle de base (CM 2003)'!G57 -> 0.024126629 | H58: ='Modèle de base (CM 2003)'!H57 -> 0.10169092 | I58: ='Modèle de base (CM 2003)'!I57 -> 0.17018122 | J58: ='Modèle de base (CM 2003)'!J57 -> 0.20296263 | K58: ='Modèle de base (CM 2003)'!K57 -> 0.2221153 | ... M58: ='Modèle de base (CM 2003)'!M57 -> 0.2547242
A59: Part de la société | C59: =1-C57 -> 0.27750032

Sheet BURKINA code minier 2003
A1: Projet aurifère_De Houndé | B1: Unités | C1: ='Modèle de base (CM 2003)'!C1 -> 2011 | D1: ='Modèle de base (CM 2003)'!D1 -> 2012 | E1: ='Modèle de base (CM 2003)'!E1 -> 2013 | F1: ='Modèle de base (CM 2003)'!F1 -> 2014 | G1: ='Modèle de base (CM 2003)'!G1 -> 2015 | H1: ='Modèle de base (CM 2003)'!H1 -> 2016 | I1: ='Modèle de base (CM 2003)'!I1 -> 2017 | J1: ='Modèle de base (CM 2003)'!J1 -> 2018 | ... M1: ='Modèle de base (CM 2003)'!M1 -> 2021
C2: ='Modèle de base (CM 2003)'!C2 -> 0 | D2: ='Modèle de base (CM 2003)'!D2 -> 0 | E2: ='Modèle de base (CM 2003)'!E2 -> 0 | F2: ='Modèle de base (CM 2003)'!F2 -> 0 | G2: ='Modèle de base (CM 2003)'!G2 -> 0 | H2: ='Modèle de base (CM 2003)'!H2 -> 0 | I2: ='Modèle de base (CM 2003)'!I2 -> 0 | J2: ='Modèle de base (CM 2003)'!J2 -> 0 | ... M2: ='Modèle de base (CM 2003)'!M2 -> 0
C3: ='Modèle de base (CM 2003)'!C3 -> 0 | D3: ='Modèle de base (CM 2003)'!D3 -> 0 | E3: ='Modèle de base (CM 2003)'!E3 -> 0 | F3: ='Modèle de base (CM 2003)'!F3 -> 0 | G3: ='Modèle de base (CM 2003)'!G3 -> 0 | H3: ='Modèle de base (CM 2003)'!H3 -> 0 | I3: ='Modèle de base (CM 2003)'!I3 -> 0 | J3: ='Modèle de base (CM 2003)'!J3 -> 0 | ... M3: ='Modèle de base (CM 2003)'!M3 -> 0
A4: Production | C4: ='Modèle de base (CM 2003)'!C4 -> 0 | D4: ='Modèle de base (CM 2003)'!D4 -> 0 | E4: ='Modèle de base (CM 2003)'!E4 -> 0 | F4: ='Modèle de base (CM 2003)'!F4 -> 0 | G4: ='Modèle de base (CM 2003)'!G4 -> 0 | H4: ='Modèle de base (CM 2003)'!H4 -> 0 | I4: ='Modèle de base (CM 2003)'!I4 -> 0 | J4: ='Modèle de base (CM 2003)'!J4 -> 0 | ... M4: ='Modèle de base (CM 2003)'!M4 -> 0
A5: Quantité Traité | B5: t | C5: ='Modèle de base (CM 2003)'!C5 -> 0 | D5: ='Modèle de base (CM 2003)'!D5 -> 0 | E5: ='Modèle de base (CM 2003)'!E5 -> 0 | F5: ='Modèle de base (CM 2003)'!F5 -> 0 | G5: ='Modèle de base (CM 2003)'!G5 -> 0 | H5: ='Modèle de base (CM 2003)'!H5 -> 0 | I5: ='Modèle de base (CM 2003)'!I5 -> 0 | J5: ='Modèle de base (CM 2003)'!J5 -> 0 | ... M5: ='Modèle de base (CM 2003)'!M5 -> 0
A6: Teneur en or | B6: g/t | C6: ='Modèle de base (CM 2003)'!C6 -> 0 | D6: ='Modèle de base (CM 2003)'!D6 -> 0 | E6: ='Modèle de base (CM 2003)'!E6 -> 0 | F6: ='Modèle de base (CM 2003)'!F6 -> 0 | G6: ='Modèle de base (CM 2003)'!G6 -> 0 | H6: ='Modèle de base (CM 2003)'!H6 -> 0 | I6: ='Modèle de base (CM 2003)'!I6 -> 0 | J6: ='Modèle de base (CM 2003)'!J6 -> 0 | ... M6: ='Modèle de base (CM 2003)'!M6 -> 0
A7: Quantité d'Or Récupéré | B7: oz | C7: ='Modèle de base (CM 2003)'!C7 -> 0 | D7: ='Modèle de base (CM 2003)'!D7 -> 0 | E7: ='Modèle de base (CM 2003)'!E7 -> 191176 | F7: ='Modèle de base (CM 2003)'!F7 -> 215238 | G7: ='Modèle de base (CM 2003)'!G7 -> 189807 | H7: ='Modèle de base (CM 2003)'!H7 -> 168325 | I7: ='Modèle de base (CM 2003)'!I7 -> 210971 | J7: ='Modèle de base (CM 2003)'!J7 -> 167700 | ... M7: ='Modèle de base (CM 2003)'!M7 -> 119370
A8: Cours de l'or | B8: =Q11 -> 1300 | C8: ='Modèle de base (CM 2003)'!C8 -> 0 | D8: ='Modèle de base (CM 2003)'!D8 -> 0 | E8: ='Modèle de base (CM 2003)'!E8 -> 1300 | F8: ='Modèle de base (CM 2003)'!F8 -> 1300 | G8: ='Modèle de base (CM 2003)'!G8 -> 1300 | H8: ='Modèle de base (CM 2003)'!H8 -> 1300 | I8: ='Modèle de base (CM 2003)'!I8 -> 1300 | J8: ='Modèle de base (CM 2003)'!J8 -> 1300 | ... M8: ='Modèle de base (CM 2003)'!M8 -> 1300
A9: Chiffre d'Affaire | B9: $ | C9: =$B$8*C7 -> 0 | D9: =$B$8*D7 -> 0 | E9: =$B$8*E7 -> 248528800 | F9: =$B$8*F7 -> 279809400 | G9: =$B$8*G7 -> 246749100 | H9: =$B$8*H7 -> 218822500 | I9: =$B$8*I7 -> 274262300 | J9: =$B$8*J7 -> 218010000 | ... M9: =$B$8*M7 -> 155181000
A10: Taux de change | B10: 493.00615 | C10: ='Modèle de base (CM 2003)'!C10 -> 0 | D10: ='Modèle de base (CM 2003)'!D10 -> 0 | E10: ='Modèle de base (CM 2003)'!E10 -> 0 | F10: ='Modèle de base (CM 2003)'!F10 -> 0 | G10: ='Modèle de base (CM 2003)'!G10 -> 0 | H10: ='Modèle de base (CM 2003)'!H10 -> 0 | I10: ='Modèle de base (CM 2003)'!I10 -> 0 | J10: ='Modèle de base (CM 2003)'!J10 -> 0 | ... M10: ='Modèle de base (CM 2003)'!M10 -> 0 | Q10: Données | R10: VAN AV IMPÔT | S10: VAN AP IMPÔT | T10: TEMI | U10: TRI AV | V10: TRI AP
A11: Taux d'actualisation | B11: =Q12 -> 0.03 | C11: ='Modèle de base (CM 2003)'!C11 -> 0 | D11: ='Modèle de base (CM 2003)'!D11 -> 0 | E11: ='Modèle de base (CM 2003)'!E11 -> 0 | F11: ='Modèle de base (CM 2003)'!F11 -> 0 | G11: ='Modèle de base (CM 2003)'!G11 -> 0 | H11: ='Modèle de base (CM 2003)'!H11 -> 0 | I11: ='Modèle de base (CM 2003)'!I11 -> 0 | J11: ='Modèle de base (CM 2003)'!J11 -> 0 | ... M11: ='Modèle de base (CM 2003)'!M11 -> 0 | P11: Cours de l'or | Q11: 1300 | R11: =C26 -> 4.3605874e+08 | S11: =C56 -> 1.730842e+08 | T11: =C57 -> 0.60307138 | U11: =C27 -> 0.27738179 | V11: =C58 -> 0.14247931
C12: ='Modèle de base (CM 2003)'!C12 -> 0 | D12: ='Modèle de base (CM 2003)'!D12 -> 0 | E12: ='Modèle de base (CM 2003)'!E12 -> 0 | F12: ='Modèle de base (CM 2003)'!F12 -> 0 | G12: ='Modèle de base (CM 2003)'!G12 -> 0 | H12: ='Modèle de base (CM 2003)'!H12 -> 0 | I12: ='Modèle de base (CM 2003)'!I12 -> 0 | J12: ='Modèle de base (CM 2003)'!J12 -> 0 | ... M12: ='Modèle de base (CM 2003)'!M12 -> 0 | P12: Taux d'actualisation | Q12: 0.03
A13: Coûts d'investissement (CAPEX) | C13: ='Modèle de base (CM 2003)'!C13 -> 0 | D13: ='Modèle de base (CM 2003)'!D13 -> 0 | E13: ='Modèle de base (CM 2003)'!E13 -> 0 | F13: ='Modèle de base (CM 2003)'!F13 -> 0 | G13: ='Modèle de base (CM 2003)'!G13 -> 0 | H13: ='Modèle de base (CM 2003)'!H13 -> 0 | I13: ='Modèle de base (CM 2003)'!I13 -> 0 | J13: ='Modèle de base (CM 2003)'!J13 -> 0 | ... M13: ='Modèle de base (CM 2003)'!M13 -> 0 | P13: IS | Q13: 0.275
A14: Coûts des construction industrielles | B14: $ | C14: ='Modèle de base (CM 2003)'!C14 -> 49760265 | D14: ='Modèle de base (CM 2003)'!D14 -> 116107284 | E14: ='Modèle de base (CM 2003)'!E14 -> 0 | F14: ='Modèle de base (CM 2003)'!F14 -> 0 | G14: ='Modèle de base (CM 2003)'!G14 -> 0 | H14: ='Modèle de base (CM 2003)'!H14 -> 0 | I14: ='Modèle de base (CM 2003)'!I14 -> 0 | J14: ='Modèle de base (CM 2003)'!J14 -> 0 | ... M14: ='Modèle de base (CM 2003)'!M14 -> 0 | P14: Taux de redevance propotionelle | Q14: 0.04
A15: Coûts des biens d'équipement | C15: ='Modèle de base (CM 2003)'!C15 -> 23685527 | D15: ='Modèle de base (CM 2003)'!D15 -> 125300533 | E15: ='Modèle de base (CM 2003)'!E15 -> 11632917 | F15: ='Modèle de base (CM 2003)'!F15 -> 3722927 | G15: ='Modèle de base (CM 2003)'!G15 -> 18272647 | H15: ='Modèle de base (CM 2003)'!H15 -> 4482500 | I15: ='Modèle de base (CM 2003)'!I15 -> 2137128 | J15: ='Modèle de base (CM 2003)'!J15 -> 1103055 | ... M15: ='Modèle de base (CM 2003)'!M15 -> 542926
A16: Autres depenses | B16: $ | C16: ='Modèle de base (CM 2003)'!C16 -> 0 | D16: ='Modèle de base (CM 2003)'!D16 -> 0 | E16: ='Modèle de base (CM 2003)'!E16 -> 1595000 | F16: ='Modèle de base (CM 2003)'!F16 -> 2708200 | G16: ='Modèle de base (CM 2003)'!G16 -> 249700 | H16: ='Modèle de base (CM 2003)'!H16 -> 2581553 | I16: ='Modèle de base (CM 2003)'!I16 -> 469553 | J16: ='Modèle de base (CM 2003)'!J16 -> 3654542 | ... M16: ='Modèle de base (CM 2003)'!M16 -> 0
A17: Coûts de réhabilitation du site | B17: $ | C17: ='Modèle de base (CM 2003)'!C17 -> 0 | D17: ='Modèle de base (CM 2003)'!D17 -> 0 | E17: ='Modèle de base (CM 2003)'!E17 -> 2830244 | F17: ='Modèle de base (CM 2003)'!F17 -> 3314368 | G17: ='Modèle de base (CM 2003)'!G17 -> 3215137 | H17: ='Modèle de base (CM 2003)'!H17 -> 3842412 | I17: ='Modèle de base (CM 2003)'!I17 -> 4018506 | J17: ='Modèle de base (CM 2003)'!J17 -> 2935298 | ... M17: ='Modèle de base (CM 2003)'!M17 -> 3165512
A18: TOTAL CAPITAL | B18: $ | C18: =SUM(C14:C17) -> 73445792 | D18: =SUM(D14:D17) -> 241407817 | E18: =SUM(E14:E17) -> 16058161 | F18: =SUM(F14:F17) -> 9745495 | G18: =SUM(G14:G17) -> 21737484 | H18: =SUM(H14:H17) -> 10906465 | I18: =SUM(I14:I17) -> 6625187 | J18: =SUM(J14:J17) -> 7692895 | ... M18: =SUM(M14:M17) -> 3708438
C19: ='Modèle de base (CM 2003)'!C19 -> 0 | D19: ='Modèle de base (CM 2003)'!D19 -> 0 | E19: ='Modèle de base (CM 2003)'!E19 -> 0 | F19: ='Modèle de base (CM 2003)'!F19 -> 0 | G19: ='Modèle de base (CM 2003)'!G19 -> 0 | H19: ='Modèle de base (CM 2003)'!H19 -> 0 | I19: ='Modèle de base (CM 2003)'!I19 -> 0 | J19: ='Modèle de base (CM 2003)'!J19 -> 0 | ... M19: ='Modèle de base (CM 2003)'!M19 -> 0
A20: Coûts d'exploitation (Opex)/hors redevance | B20: $ | C20: ='Modèle de base (CM 2003)'!C20 -> 0 | D20: ='Modèle de base (CM 2003)'!D20 -> 0 | E20: ='Modèle de base (CM 2003)'!E20 -> 115668594 | F20: ='Modèle de base (CM 2003)'!F20 -> 128519703 | G20: ='Modèle de base (CM 2003)'!G20 -> 131246978 | H20: ='Modèle de base (CM 2003)'!H20 -> 152348402 | I20: ='Modèle de base (CM 2003)'!I20 -> 157632470 | J20: ='Modèle de base (CM 2003)'!J20 -> 132358509 | ... M20: ='Modèle de base (CM 2003)'!M20 -> 9542514
A21: Coûts d'exploitation moyen (Opex) /hors redevance | B21: $/oz | C21: ='Modèle de base (CM 2003)'!C21 -> 0 | D21: ='Modèle de base (CM 2003)'!D21 -> 0 | E21: =E20/E7 -> 605.03721 | F21: =F20/F7 -> 597.10508 | G21: =G20/G7 -> 691.47596 | H21: =H20/H7 -> 905.08482 | I21: =I20/I7 -> 747.17601 | J21: =J20/J7 -> 789.25766 | K21: =K20/K7 -> 784.16128 | L21: =L20/L7 -> 634.66598 | M21: =M20/M7 -> 79.940638
C22: ='Modèle de base (CM 2003)'!C22 -> 0 | D22: ='Modèle de base (CM 2003)'!D22 -> 0 | E22: ='Modèle de base (CM 2003)'!E22 -> 0 | F22: ='Modèle de base (CM 2003)'!F22 -> 0 | G22: ='Modèle de base (CM 2003)'!G22 -> 0 | H22: ='Modèle de base (CM 2003)'!H22 -> 0 | I22: ='Modèle de base (CM 2003)'!I22 -> 0 | J22: ='Modèle de base (CM 2003)'!J22 -> 0 | ... M22: ='Modèle de base (CM 2003)'!M22 -> 0
A23: Coût Totaux | C23: =C$18+C$20 -> 73445792 | D23: =D$18+D$20 -> 241407817 | E23: =E$18+E$20 -> 131726755 | F23: =F$18+F$20 -> 138265198 | G23: =G$18+G$20 -> 152984462 | H23: =H$18+H$20 -> 163254867 | I23: =I$18+I$20 -> 164257657 | J23: =J$18+J$20 -> 140051404 | ... M23: =M$18+M$20 -> 13250952
C24: ='Modèle de base (CM 2003)'!C24 -> 0 | D24: ='Modèle de base (CM 2003)'!D24 -> 0 | E24: ='Modèle de base (CM 2003)'!E24 -> 0 | F24: ='Modèle de base (CM 2003)'!F24 -> 0 | G24: ='Modèle de base (CM 2003)'!G24 -> 0 | H24: ='Modèle de base (CM 2003)'!H24 -> 0 | I24: ='Modèle de base (CM 2003)'!I24 -> 0 | J24: ='Modèle de base (CM 2003)'!J24 -> 0 | ... M24: ='Modèle de base (CM 2003)'!M24 -> 0
A25: Cash-flows avant impôts | C25: =C$9-C$23 -> -73445792 | D25: =D$9-D$23 -> -241407817 | E25: =E$9-E$23 -> 116802045 | F25: =F$9-F$23 -> 141544202 | G25: =G$9-G$23 -> 93764638 | H25: =H$9-H$23 -> 55567633 | I25: =I$9-I$23 -> 110004643 | J25: =J$9-J$23 -> 77958596 | ... M25: =M$9-M$23 -> 141930048
A26: VAN avant impôts | C26: =NPV($B$11,C25:M25) -> 4.3605874e+08 | D26: ='Modèle de base (CM 2003)'!D26 -> 0 | E26: ='Modèle de base (CM 2003)'!E26 -> 0 | F26: ='Modèle de base (CM 2003)'!F26 -> 0 | G26: ='Modèle de base (CM 2003)'!G26 -> 0 | H26: ='Modèle de base (CM 2003)'!H26 -> 0 | I26: ='Modèle de base (CM 2003)'!I26 -> 0 | J26: ='Modèle de base (CM 2003)'!J26 -> 0 | K26: ='Modèle de base (CM 2003)'!K26 -> 0 | ... M26: ='Modèle de base (CM 2003)'!M26 -> 0
A27: TRI avant impôts | C27: =IRR(C25:M25) -> 0.27738179 | D27: ='Modèle de base (CM 2003)'!D27 -> 0 | E27: ='Modèle de base (CM 2003)'!E27 -> -0.3913088 | F27: ='Modèle de base (CM 2003)'!F27 -> 0.11243079 | G27: ='Modèle de base (CM 2003)'!G27 -> 0.2768997 | H27: ='Modèle de base (CM 2003)'!H27 -> 0.3407976 | I27: ='Modèle de base (CM 2003)'!I27 -> 0.40012659 | J27: ='Modèle de base (CM 2003)'!J27 -> 0.42540794 | K27: ='Modèle de base (CM 2003)'!K27 -> 0.43824983 | ... M27: ='Modèle de base (CM 2003)'!M27 -> 0.45818507
C28: ='Modèle de base (CM 2003)'!C28 -> 0 | D28: ='Modèle de base (CM 2003)'!D28 -> 0 | E28: ='Modèle de base (CM 2003)'!E28 -> 0 | F28: ='Modèle de base (CM 2003)'!F28 -> 0 | G28: ='Modèle de base (CM 2003)'!G28 -> 0 | H28: ='Modèle de base (CM 2003)'!H28 -> 0 | I28: ='Modèle de base (CM 2003)'!I28 -> 0 | J28: ='Modèle de base (CM 2003)'!J28 -> 0 | ... M28: ='Modèle de base (CM 2003)'!M28 -> 0
A29: Droits fixes (6000$/Km2 ) | B29: 6000 | C29: =B$29*C$32 -> 139200 | D29: ='Modèle de base (CM 2003)'!D29 -> 0 | E29: ='Modèle de base (CM 2003)'!E29 -> 0 | F29: ='Modèle de base (CM 2003)'!F29 -> 0 | G29: ='Modèle de base (CM 2003)'!G29 -> 0 | H29: ='Modèle de base (CM 2003)'!H29 -> 0 | I29: ='Modèle de base (CM 2003)'!I29 -> 0 | J29: ='Modèle de base (CM 2003)'!J29 -> 0 | K29: ='Modèle de base (CM 2003)'!K29 -> 0 | ... M29: ='Modèle de base (CM 2003)'!M29 -> 0
C30: ='Modèle de base (CM 2003)'!C30 -> 0 | D30: ='Modèle de base (CM 2003)'!D30 -> 0 | E30: ='Modèle de base (CM 2003)'!E30 -> 0 | F30: ='Modèle de base (CM 2003)'!F30 -> 0 | G30: ='Modèle de base (CM 2003)'!G30 -> 0 | H30: ='Modèle de base (CM 2003)'!H30 -> 0 | I30: ='Modèle de base (CM 2003)'!I30 -> 0 | J30: ='Modèle de base (CM 2003)'!J30 -> 0 | ... M30: ='Modèle de base (CM 2003)'!M30 -> 0
C31: ='Modèle de base (CM 2003)'!C31 -> 0 | D31: ='Modèle de base (CM 2003)'!D31 -> 0 | E31: ='Modèle de base (CM 2003)'!E31 -> 0 | F31: ='Modèle de base (CM 2003)'!F31 -> 0 | G31: ='Modèle de base (CM 2003)'!G31 -> 0 | H31: ='Modèle de base (CM 2003)'!H31 -> 0 | I31: ='Modèle de base (CM 2003)'!I31 -> 0 | J31: ='Modèle de base (CM 2003)'!J31 -> 0 | ... M31: ='Modèle de base (CM 2003)'!M31 -> 0
A32: Superficie de la mine | B32: 150 | C32: ='Modèle de base (CM 2003)'!C32 -> 23.2 | D32: ='Modèle de base (CM 2003)'!D32 -> 23.2 | E32: ='Modèle de base (CM 2003)'!E32 -> 23.2 | F32: ='Modèle de base (CM 2003)'!F32 -> 23.2 | G32: ='Modèle de base (CM 2003)'!G32 -> 23.2 | H32: ='Modèle de base (CM 2003)'!H32 -> 23.2 | I32: ='Modèle de base (CM 2003)'!I32 -> 23.2 | J32: ='Modèle de base (CM 2003)'!J32 -> 23.2 | ... M32: ='Modèle de base (CM 2003)'!M32 -> 23.2
A33: Redevance superficière | C33: =C$32*$B$32 -> 3480 | D33: =D$32*$B$32 -> 3480 | E33: =E$32*$B$32 -> 3480 | F33: =F$32*$B$32 -> 3480 | G33: =G$32*$B$32 -> 3480 | H33: =H$32*$B$32 -> 3480 | I33: =I$32*$B$32 -> 3480 | J33: =J$32*$B$32 -> 3480 | ... M33: =M$32*$B$32 -> 3480
C34: ='Modèle de base (CM 2003)'!C34 -> 0 | D34: ='Modèle de base (CM 2003)'!D34 -> 0 | E34: ='Modèle de base (CM 2003)'!E34 -> 0 | F34: ='Modèle de base (CM 2003)'!F34 -> 0 | G34: ='Modèle de base (CM 2003)'!G34 -> 0 | H34: ='Modèle de base (CM 2003)'!H34 -> 0 | I34: ='Modèle de base (CM 2003)'!I34 -> 0 | J34: ='Modèle de base (CM 2003)'!J34 -> 0 | ... M34: ='Modèle de base (CM 2003)'!M34 -> 0
A35: Taxe sur les substances minières | C35: ='Modèle de base (CM 2003)'!C35 -> 0 | D35: ='Modèle de base (CM 2003)'!D35 -> 0 | E35: ='Modèle de base (CM 2003)'!E35 -> 0 | F35: ='Modèle de base (CM 2003)'!F35 -> 0 | G35: ='Modèle de base (CM 2003)'!G35 -> 0 | H35: ='Modèle de base (CM 2003)'!H35 -> 0 | I35: ='Modèle de base (CM 2003)'!I35 -> 0 | J35: ='Modèle de base (CM 2003)'!J35 -> 0 | ... M35: ='Modèle de base (CM 2003)'!M35 -> 0
A36: taux de la taxe | B36: =Q14 -> 0.04 | D36: ='Modèle de base (CM 2003)'!D36 -> 0 | E36: 0.035 | F36: 0.035 | G36: 0.035 | H36: 0.035 | I36: 0.035 | J36: 0.035 | K36: 0.035 | L36: 0.035 | M36: 0.035
A37: Montant de la redevance | C37: =$B$36*C$9 -> 0 | D37: =$B$36*D$9 -> 0 | E37: =$B$36*E$9 -> 9941152 | F37: =$B$36*F$9 -> 11192376 | G37: =$B$36*G$9 -> 9869964 | H37: =$B$36*H$9 -> 8752900 | I37: =$B$36*I$9 -> 10970492 | J37: =$B$36*J$9 -> 8720400 | ... M37: =$B$36*M$9 -> 6207240
C38: ='Modèle de base (CM 2003)'!C38 -> 0 | D38: ='Modèle de base (CM 2003)'!D38 -> 0 | E38: ='Modèle de base (CM 2003)'!E38 -> 0 | F38: ='Modèle de base (CM 2003)'!F38 -> 0 | G38: ='Modèle de base (CM 2003)'!G38 -> 0 | H38: ='Modèle de base (CM 2003)'!H38 -> 0 | I38: ='Modèle de base (CM 2003)'!I38 -> 0 | J38: ='Modèle de base (CM 2003)'!J38 -> 0 | ... M38: ='Modèle de base (CM 2003)'!M38 -> 0
A39: Charges d'amortissement | C39: ='Modèle de base (CM 2003)'!C39 -> 14450237 | D39: ='Modèle de base (CM 2003)'!D39 -> 72391495 | E39: ='Modèle de base (CM 2003)'!E39 -> 54722766 | F39: ='Modèle de base (CM 2003)'!F39 -> 41469139 | G39: ='Modèle de base (CM 2003)'!G39 -> 42554951 | H39: ='Modèle de base (CM 2003)'!H39 -> 38090104 | I39: ='Modèle de base (CM 2003)'!I39 -> 22807098 | J39: ='Modèle de base (CM 2003)'!J39 -> 20561890 | ... M39: ='Modèle de base (CM 2003)'!M39 -> 15427244
A40: Contribution au développement local | B40: 0.01 | C40: =C9*$B$40 -> 0 | D40: =D9*$B$40 -> 0 | E40: =E9*$B$40 -> 2485288 | F40: =F9*$B$40 -> 2798094 | G40: =G9*$B$40 -> 2467491 | H40: =H9*$B$40 -> 2188225 | I40: =I9*$B$40 -> 2742623 | J40: =J9*$B$40 -> 2180100 | ... M40: =M9*$B$40 -> 1551810
C41: ='Modèle de base (CM 2003)'!C40 -> 0 | D41: ='Modèle de base (CM 2003)'!D40 -> 0 | E41: ='Modèle de base (CM 2003)'!E40 -> 0 | F41: ='Modèle de base (CM 2003)'!F40 -> 0 | G41: ='Modèle de base (CM 2003)'!G40 -> 0 | H41: ='Modèle de base (CM 2003)'!H40 -> 0 | I41: ='Modèle de base (CM 2003)'!I40 -> 0 | J41: ='Modèle de base (CM 2003)'!J40 -> 0 | ... M41: ='Modèle de base (CM 2003)'!M40 -> 0
A42: Bénéfice imposable | C42: =C9-(C$23+C$29+C$33+C$37+C$39) -> -88038709 | D42: =D9-(D$23+D$29+D$33+D$37+D$39) -> -3.1380279e+08 | E42: =E9-(E$23+E$29+E$33+E$37+E$39) -> 52134647 | F42: =F9-(F$23+F$29+F$33+F$37+F$39) -> 88879207 | G42: =G9-(G$23+G$29+G$33+G$37+G$39) -> 41336243 | H42: =H9-(H$23+H$29+H$33+H$37+H$39) -> 8721148.7 | I42: =I9-(I$23+I$29+I$33+I$37+I$39) -> 76223573 | J42: =J9-(J$23+J$29+J$33+J$37+J$39) -> 48672826 | ... M42: =M9-(M$23+M$29+M$33+M$37+M$39) -> 1.2029208e+08
A43: Taux IS | B43: =Q13 -> 0.275 | C43: ='Modèle de base (CM 2003)'!C42 -> 0 | D43: ='Modèle de base (CM 2003)'!D42 -> 0 | E43: 0.3 | F43: 0.3 | G43: 0.3 | H43: 0.3 | I43: 0.3 | J43: 0.3 | K43: 0.3 | L43: 0.3 | M43: 0.3
A44: Montant IMF | C44: ='Modèle de base (CM 2003)'!C43 -> 0 | D44: ='Modèle de base (CM 2003)'!D43 -> 0 | E44: ='Modèle de base (CM 2003)'!E43 -> 0 | F44: ='Modèle de base (CM 2003)'!F43 -> 0 | G44: ='Modèle de base (CM 2003)'!G43 -> 0 | H44: ='Modèle de base (CM 2003)'!H43 -> 0 | I44: ='Modèle de base (CM 2003)'!I43 -> 0 | J44: ='Modèle de base (CM 2003)'!J43 -> 1341600 | ... M44: ='Modèle de base (CM 2003)'!M43 -> 954960
A45: IS/IMF | C45: =IF($B$43*C$42>C$44,C$42*$B$43,0) -> 0 | D45: =IF($B$43*D$42>D$44,D$42*$B$43,0) -> 0 | E45: =IF($B$43*E$42>E$44,E$42*$B$43,0) -> 14337028 | F45: =IF($B$43*F$42>F$44,F$42*$B$43,0) -> 24441782 | G45: =IF($B$43*G$42>G$44,G$42*$B$43,0) -> 11367467 | H45: =IF($B$43*H$42>H$44,H$42*$B$43,0) -> 2398315.9 | I45: =IF($B$43*I$42>I$44,I$42*$B$43,0) -> 20961482 | J45: =IF($B$43*J$42>J$44,J$42*$B$43,0) -> 13385027 | ... M45: =IF($B$43*M$42>M$44,M$42*$B$43,0) -> 33080323
C46: ='Modèle de base (CM 2003)'!C45 -> 0 | D46: ='Modèle de base (CM 2003)'!D45 -> 0 | E46: ='Modèle de base (CM 2003)'!E45 -> 0 | F46: ='Modèle de base (CM 2003)'!F45 -> 0 | G46: ='Modèle de base (CM 2003)'!G45 -> 0 | H46: ='Modèle de base (CM 2003)'!H45 -> 0 | I46: ='Modèle de base (CM 2003)'!I45 -> 0 | J46: ='Modèle de base (CM 2003)'!J45 -> 0 | ... M46: ='Modèle de base (CM 2003)'!M45 -> 0
A47: Résultat après impôt | C47: =C$42-C$45 -> -88038709 | D47: =D$42-D$45 -> -3.1380279e+08 | E47: =E$42-E$45 -> 37797619 | F47: =F$42-F$45 -> 64437425 | G47: =G$42-G$45 -> 29968776 | H47: =H$42-H$45 -> 6322832.8 | I47: =I$42-I$45 -> 55262090 | J47: =J$42-J$45 -> 35287799 | ... M47: =M$42-M$45 -> 87211761
A48: Participation de l'Etat | B48: 0.1 | C48: ='Modèle de base (CM 2003)'!C47 -> 0 | D48: ='Modèle de base (CM 2003)'!D47 -> 0 | E48: ='Modèle de base (CM 2003)'!E47 -> 0 | F48: ='Modèle de base (CM 2003)'!F47 -> 0 | G48: ='Modèle de base (CM 2003)'!G47 -> 0 | H48: ='Modèle de base (CM 2003)'!H47 -> 0 | I48: ='Modèle de base (CM 2003)'!I47 -> 0 | J48: ='Modèle de base (CM 2003)'!J47 -> 0 | ... M48: ='Modèle de base (CM 2003)'!M47 -> 0
A49: Dividende de l'Etat | C49: =IF(C47>0,C47*$B$48,0) -> 0 | D49: =IF(D47>0,D47*$B$48,0) -> 0 | E49: =IF(E47>0,E47*$B$48,0) -> 3779761.9 | F49: =IF(F47>0,F47*$B$48,0) -> 6443742.5 | G49: =IF(G47>0,G47*$B$48,0) -> 2996877.6 | H49: =IF(H47>0,H47*$B$48,0) -> 632283.28 | I49: =IF(I47>0,I47*$B$48,0) -> 5526209 | J49: =IF(J47>0,J47*$B$48,0) -> 3528779.9 | ... M49: =IF(M47>0,M47*$B$48,0) -> 8721176.1
A50: Part de la société | C50: =C$47-C$49 -> -88038709 | D50: =D$47-D$49 -> -3.1380279e+08 | E50: =E$47-E$49 -> 34017857 | F50: =F$47-F$49 -> 57993682 | G50: =G$47-G$49 -> 26971899 | H50: =H$47-H$49 -> 5690549.5 | I50: =I$47-I$49 -> 49735881 | J50: =J$47-J$49 -> 31759019 | ... M50: =M$47-M$49 -> 78490585
A51: Impôt sur les dividendes | B51: =10% -> 0.1 | C51: =IF(C50>0,C50*$B$51,0) -> 0 | D51: =IF(D50>0,D50*$B$51,0) -> 0 | E51: =IF(E50>0,E50*$B$51,0) -> 3401785.7 | F51: =IF(F50>0,F50*$B$51,0) -> 5799368.2 | G51: =IF(G50>0,G50*$B$51,0) -> 2697189.9 | H51: =IF(H50>0,H50*$B$51,0) -> 569054.95 | I51: =IF(I50>0,I50*$B$51,0) -> 4973588.1 | J51: =IF(J50>0,J50*$B$51,0) -> 3175901.9 | ... M51: =IF(M50>0,M50*$B$51,0) -> 7849058.5
C52: ='Modèle de base (CM 2003)'!C51 -> 0 | D52: ='Modèle de base (CM 2003)'!D51 -> 0 | E52: ='Modèle de base (CM 2003)'!E51 -> 0 | F52: ='Modèle de base (CM 2003)'!F51 -> 0 | G52: ='Modèle de base (CM 2003)'!G51 -> 0 | H52: ='Modèle de base (CM 2003)'!H51 -> 0 | I52: ='Modèle de base (CM 2003)'!I51 -> 0 | J52: ='Modèle de base (CM 2003)'!J51 -> 0 | ... M52: ='Modèle de base (CM 2003)'!M51 -> 0
C53: ='Modèle de base (CM 2003)'!C52 -> 0 | D53: ='Modèle de base (CM 2003)'!D52 -> 0 | E53: ='Modèle de base (CM 2003)'!E52 -> 0 | F53: ='Modèle de base (CM 2003)'!F52 -> 0 | G53: ='Modèle de base (CM 2003)'!G52 -> 0 | H53: ='Modèle de base (CM 2003)'!H52 -> 0 | I53: ='Modèle de base (CM 2003)'!I52 -> 0 | J53: ='Modèle de base (CM 2003)'!J52 -> 0 | ... M53: ='Modèle de base (CM 2003)'!M52 -> 0
A54: Recettes totales de l'Etat | C54: =C$29+C$33+C$37+C$40+C$45+C$49+C$51 -> 142680 | D54: =D$29+D$33+D$37+D$40+D$45+D$49+D$51 -> 3480 | E54: =E$29+E$33+E$37+E$40+E$45+E$49+E$51 -> 33948496 | F54: =F$29+F$33+F$37+F$40+F$45+F$49+F$51 -> 50678843 | G54: =G$29+G$33+G$37+G$40+G$45+G$49+G$51 -> 29402469 | H54: =H$29+H$33+H$37+H$40+H$45+H$49+H$51 -> 14544259 | I54: =I$29+I$33+I$37+I$40+I$45+I$49+I$51 -> 45177875 | J54: =J$29+J$33+J$37+J$40+J$45+J$49+J$51 -> 30993689 | ... M54: =M$29+M$33+M$37+M$40+M$45+M$49+M$51 -> 57413087
A55: Cash-Flows après imôts | C55: =C$25-C$54 -> -73588472 | D55: =D$25-D$54 -> -241411297 | E55: =E$25-E$54 -> 82853549 | F55: =F$25-F$54 -> 90865359 | G55: =G$25-G$54 -> 64362169 | H55: =H$25-H$54 -> 41023374 | I55: =I$25-I$54 -> 64826768 | J55: =J$25-J$54 -> 46964907 | ... M55: =M$25-M$54 -> 84516961
A56: VAN après impôts | C56: =NPV($B$11,C55:M55) -> 1.730842e+08 | D56: ='Modèle de base (CM 2003)'!D55 -> 0 | E56: ='Modèle de base (CM 2003)'!E55 -> 0 | F56: ='Modèle de base (CM 2003)'!F55 -> 0 | G56: ='Modèle de base (CM 2003)'!G55 -> 0 | H56: ='Modèle de base (CM 2003)'!H55 -> 0 | I56: ='Modèle de base (CM 2003)'!I55 -> 0 | J56: ='Modèle de base (CM 2003)'!J55 -> 0 | K56: ='Modèle de base (CM 2003)'!K55 -> 0 | ... M56: ='Modèle de base (CM 2003)'!M55 -> 0
A57: TEMI | C57: =1-(C56/C26) -> 0.60307138 | D57: ='Modèle de base (CM 2003)'!D56 -> 0 | E57: ='Modèle de base (CM 2003)'!E56 -> 0 | F57: ='Modèle de base (CM 2003)'!F56 -> 0 | G57: ='Modèle de base (CM 2003)'!G56 -> 0 | H57: ='Modèle de base (CM 2003)'!H56 -> 0 | I57: ='Modèle de base (CM 2003)'!I56 -> 0 | J57: ='Modèle de base (CM 2003)'!J56 -> 0 | K57: ='Modèle de base (CM 2003)'!K56 -> 0 | ... M57: ='Modèle de base (CM 2003)'!M56 -> 0
A58: TRI après impôts | C58: =IRR(C55:M55) -> 0.14247931 | D58: ='Modèle de base (CM 2003)'!D57 -> 0 | E58: ='Modèle de base (CM 2003)'!E57 -> 0 | F58: ='Modèle de base (CM 2003)'!F57 -> -0.1492555 | G58: ='Modèle de base (CM 2003)'!G57 -> 0.024126629 | H58: ='Modèle de base (CM 2003)'!H57 -> 0.10169092 | I58: ='Modèle de base (CM 2003)'!I57 -> 0.17018122 | J58: ='Modèle de base (CM 2003)'!J57 -> 0.20296263 | K58: ='Modèle de base (CM 2003)'!K57 -> 0.2221153 | ... M58: ='Modèle de base (CM 2003)'!M57 -> 0.2547242
A59: Part de la société | C59: =1-C57 -> 0.39692862

Sheet Données fiscales
A1: Phase d'investissement
A2: Phase d'exploitation
C4: 2011 | D4: 2012 | E4: 2013 | F4: 2014 | G4: 2015 | H4: 2016 | I4: 2017 | J4: 2018 | K4: 2019 | L4: 2020 | M4: 2021
A5: Convention (identique au code de 2003) | C5: 2011 | D5: 2012 | E5: 2013 | F5: 2014 | G5: 2015 | H5: 2016 | I5: 2017 | J5: 2018 | K5: 2019 | L5: 2020 | M5: 2021
A6: Impot sur les sociétés
A7: Taux | C7: 0 | D7: 0 | E7: =27.5%-10% -> 0.175 | F7: =27.5%-10% -> 0.175 | G7: =27.5%-10% -> 0.175 | H7: =27.5%-10% -> 0.175 | I7: =27.5%-10% -> 0.175 | J7: =27.5%-10% -> 0.175 | K7: =27.5%-10% -> 0.175 | L7: =27.5%-10% -> 0.175 | M7: =27.5%-10% -> 0.175
A8: Amortissement
A9: IMF
A10: Minimum | E10: =H38 -> 0 | F10: =I38 -> 0 | G10: =J38 -> 0 | H10: =K38 -> 0 | I10: =L38 -> 0 | J10: 1000000 | K10: 1000000 | L10: 1000000 | M10: 1000000
A11: Taux | H11: =H39 -> 0 | I11: =I39 -> 0 | J11: =J39 -> 0 | K11: =K39 -> 0 | L11: =L39 -> 0 | M11: =M39 -> 0
A12: Impot sur les dividendes(IRCM) | E12: 0.0625 | F12: 0.0625 | G12: 0.0625 | H12: 0.0625 | I12: 0.0625 | J12: 0.0625 | K12: 0.0625 | L12: 0.0625 | M12: 0.0625
A13: Taxe sur les intérets (IRCM) | E13: 0.0625 | F13: 0.0625 | G13: 0.0625 | H13: 0.0625 | I13: 0.0625 | J13: 0.0625 | K13: 0.0625 | L13: 0.0625 | M13: 0.0625
A14: Taxe sur la valeur ajoutée
A15: Droits d'enregistrement
A16: Patente
A17: Taxe patronale d'apprentissage
A18: Taxe sur les biens de main morte
A20: Droit de douane
A21: Redevance statistique
A22: Prélèvements communautaires
A23: Autres droits et taxes de douanes
A24: Taux cumulé
A26: Revedances minières
A27: Redevances fixes
... A30: Fonds de réhabilitation
A33: Code minier 2003 | C33: 2011 | D33: 2012 | E33: 2013 | F33: 2014 | G33: 2015 | H33: 2016 | I33: 2017 | J33: 2018 | K33: 2019 | L33: 2020 | M33: 2021
A34: Impot sur les sociétés
A35: Taux | E35: 0.175 | F35: 0.175 | G35: 0.175 | H35: 0.175 | I35: 0.175 | J35: 0.175 | K35: 0.175 | L35: 0.175 | M35: 0.175
A36: Amortissement
A37: IMF
A38: Minimum | H38: 0 | I38: 0 | J38: 0 | K38: 0 | L38: 0 | M38: 0
A39: Taux | H39: 0 | I39: 0 | J39: 0 | K39: 0 | L39: 0 | M39: 0
A40: Impot sur les dividendes(IRCM) | C40: 0.0625 | D40: 0.0625 | E40: 0.0625 | F40: 0.0625 | G40: 0.0625 | H40: 0.0625 | I40: 0.0625 | J40: 0.0625 | K40: 0.0625 | L40: 0.0625 | M40: 0.0625
A41: Taxe sur les intérets (IRCM) | E41: 0.0625 | F41: 0.0625 | G41: 0.0625 | H41: 0.0625 | I41: 0.0625 | J41: 0.0625 | K41: 0.0625 | L41: 0.0625 | M41: 0.0625
A42: Taxe sur la valeur ajoutée | H42: 0 | I42: 0 | J42: 0 | K42: 0 | L42: 0 | M42: 0
A43: Droits d'enregistrement | H43: 0 | I43: 0 | J43: 0 | K43: 0 | L43: 0 | M43: 0
A44: Patente
A45: Droit fixe | H45: 0 | I45: 0 | J45: 0 | K45: 0 | L45: 0 | M45: 0
A46: Droit proportionnel | H46: 0 | I46: 0 | J46: 0 | K46: 0 | L46: 0 | M46: 0
A47: Taxe patronale d'apprentissage | J47: =$G$109/2 -> 0 | K47: =$G$109/2 -> 0 | L47: =$G$109/2 -> 0 | M47: =$G$109/2 -> 0
A48: Taxe sur les biens de main morte
A50: Droit de douane | H50: =0 -> 0 | I50: 0 | J50: 0 | K50: 0 | L50: 0 | M50: 0
A51: Redevance statistique | H51: =$G$116 -> 0 | I51: =$G$116 -> 0 | J51: 0 | K51: 0 | L51: 0 | M51: 0
A52: Prélèvements communautaires | H52: =$G$117 -> 0 | I52: =$G$117 -> 0 | J52: 0 | K52: 0 | L52: 0 | M52: 0
A53: Autres droits et taxes de douanes | H53: =G118 -> 0 | I53: 0 | J53: 0 | K53: 0 | L53: 0 | M53: 0
A54: Taux cumulé | E54: 0.075 | F54: 0.075 | G54: 0.075 | H54: 0.075 | I54: 0.075 | J54: 0.075 | K54: 0.075 | L54: 0.075 | M54: 0.075
A56: Revedances minières
A57: Redevances fixes | C57: =5000000+500000 -> 5500000
A58: Redevances superficiaires | C58: 7500000 | D58: 7500000 | E58: 7500000 | F58: 7500000 | G58: 7500000 | H58: 10000000 | I58: 10000000 | J58: 10000000 | K58: 10000000 | L58: 10000000 | M58: 15000000
A59: Redevances proportionnelles (cours 1100 et 1300) | E59: 0.04 | F59: 0.04 | G59: 0.04 | H59: 0.04 | I59: 0.04 | J59: 0.04 | K59: 0.04 | L59: 0.04 | M59: 0.04
A60: Redevances proportionnelles (cours de 1000) | E60: 0.03 | F60: 0.03 | G60: 0.03 | H60: 0.03 | I60: 0.03 | J60: 0.03 | K60: 0.03 | L60: 0.03 | M60: 0.03
A61: Redevances proportionnelles (cours de 1600) | E61: 0.05 | F61: 0.05 | G61: 0.05 | H61: 0.05 | I61: 0.05 | J61: 0.05 | K61: 0.05 | L61: 0.05 | M61: 0.05
A62: Fonds de réhabilitation
A65: Code minier 2015 | C65: =C4 -> 2011 | D65: =D4 -> 2012 | E65: =E4 -> 2013 | F65: =F4 -> 2014 | G65: =G4 -> 2015 | H65: =H4 -> 2016 | I65: =I4 -> 2017 | J65: =J4 -> 2018 | ... M65: =M4 -> 2021
A66: Impot sur les sociétés
A67: Taux | C67: =C100 -> 0 | D67: =D100 -> 0 | E67: 0.275 | F67: 0.275 | G67: 0.275 | H67: 0.275 | I67: 0.275 | J67: 0.275 | K67: 0.275 | L67: 0.275 | M67: 0.275
A68: Amortissement
A69: IMF
A70: Minimum | H70: 0 | I70: 0 | J70: 0 | K70: 0 | L70: 0 | M70: 0
A71: Taux | H71: 0 | I71: 0 | J71: 0 | K71: 0 | L71: 0 | M71: 0
A72: Impot sur les dividendes(IRCM) | E72: 0.0625 | F72: 0.0625 | G72: 0.0625 | H72: 0.0625 | I72: 0.0625 | J72: 0.0625 | K72: 0.0625 | L72: 0.0625 | M72: 0.0625
A73: Taxe sur les intérets (IRCM) | E73: 0.0625 | F73: 0.0625 | G73: 0.0625 | H73: 0.0625 | I73: 0.0625 | J73: 0.0625 | K73: 0.0625 | L73: 0.0625 | M73: 0.0625
A74: Taxe sur la valeur ajoutée | H74: 0 | I74: 0 | J74: 0 | K74: 0 | L74: 0 | M74: 0
A75: Droits d'enregistrement | H75: 0 | I75: 0 | J75: 0 | K75: 0 | L75: 0 | M75: 0
A76: Patente
A77: Droit fixe | H77: 0 | I77: 0 | J77: 0 | K77: 0 | L77: 0 | M77: 0
A78: Droit proportionnel | H78: 0 | I78: 0 | J78: 0 | K78: 0 | L78: 0 | M78: 0
A79: Taxe patronale d'apprentissage | J79: 0 | K79: 0 | L79: 0 | M79: 0
A80: Taxe sur les biens de main morte
A82: Droit de douane | H82: 0 | I82: 0 | J82: 0 | K82: 0 | L82: 0 | M82: 0
A83: Redevance statistique | H83: 0 | I83: 0 | J83: 0 | K83: 0 | L83: 0 | M83: 0
A84: Prélèvements communautaires | H84: 0 | I84: 0 | J84: 0 | K84: 0 | L84: 0 | M84: 0
A85: Autres droits et taxes de douanes | H85: 0 | I85: 0 | J85: 0 | K85: 0 | L85: 0 | M85: 0
A86: Taux cumulé | J86: 0.075 | K86: 0.075 | L86: 0.075 | M86: 0.075
A88: Revedances minières
A89: Redevances fixes | C89: 10000000
A90: Redevances superficiaires | C90: =7500000/12 -> 625000 | D90: 7500000 | E90: 7500000 | F90: 7500000 | G90: 7500000 | H90: 10000000 | I90: 10000000 | J90: 10000000 | K90: 10000000 | L90: 10000000 | M90: 15000000
A91: Redevances proportionnelles (cours 1100 et 1300) | E91: 0.04 | F91: 0.04 | G91: 0.04 | H91: 0.04 | I91: 0.04 | J91: 0.04 | K91: 0.04 | L91: 0.04 | M91: 0.04
A92: Redevances proportionnelles (cours de 1000) | E92: 0.03 | F92: 0.03 | G92: 0.03 | H92: 0.03 | I92: 0.03 | J92: 0.03 | K92: 0.03 | L92: 0.03 | M92: 0.03
A93: Redevances proportionnelles (cours de 1600) | E93: 0.05 | F93: 0.05 | G93: 0.05 | H93: 0.05 | I93: 0.05 | J93: 0.05 | K93: 0.05 | L93: 0.05 | M93: 0.05
A94: Fonds de réhabilitation
A95: Fonds de développement local | E95: 0.01 | F95: 0.01 | G95: 0.01 | H95: 0.01 | I95: 0.01 | J95: 0.01 | K95: 0.01 | L95: 0.01 | M95: 0.01
A98: Droit commun (CGI et autres textes) | C98: 2011 | D98: 2012 | E98: 2013 | F98: 2014 | G98: 2015 | H98: 2016 | I98: 2017 | J98: 2018 | K98: 2019 | L98: 2020 | M98: 2021
A99: Impot sur les sociétés
A100: Taux | E100: =27.5% -> 0.275 | F100: =27.5% -> 0.275 | G100: =27.5% -> 0.275 | H100: =27.5% -> 0.275 | I100: =27.5% -> 0.275 | J100: =27.5% -> 0.275 | K100: =27.5% -> 0.275 | L100: =27.5% -> 0.275 | M100: =27.5% -> 0.275
A101: Amortissement
A102: IMF
A103: Montant minimum | G103: 1000000 | H103: 1000000 | I103: 1000000 | J103: 1000000 | K103: 1000000 | L103: 1000000 | M103: 1000000
A104: Taux | E104: 0.005 | F104: 0.005 | G104: 0.005 | H104: 0.005 | I104: 0.005 | J104: 0.005 | K104: 0.005 | L104: 0.005 | M104: 0.005
A105: Impot sur les dividendes(IRCM) | E105: 0.125 | F105: 0.125 | G105: 0.125 | H105: 0.125 | I105: 0.125 | J105: 0.125 | K105: 0.125 | L105: 0.125 | M105: 0.125
A106: Taxe sur les intérets (IRCM) | E106: 0.125 | F106: 0.125 | G106: 0.125 | H106: 0.125 | I106: 0.125 | J106: 0.125 | K106: 0.125 | L106: 0.125 | M106: 0.125
A107: Taxe sur la valeur ajoutée | E107: 0.18 | F107: 0.18 | G107: 0.18 | H107: 0.18 | I107: 0.18 | J107: 0.18 | K107: 0.18 | L107: 0.18 | M107: 0.18
A108: Droits d'enregistrement
A109: Patente
A110: Droit fixe | C110: 5500000 | E110: Barème | F110: Barème | G110: Barème | H110: Barème | I110: Barème | J110: Barème | K110: Barème | L110: Barème | M110: Barème
A111: Droit proportionnel | E111: 0.08 | F111: 0.08 | G111: 0.08 | H111: 0.08 | I111: 0.08 | J111: 0.08 | K111: 0.08 | L111: 0.08 | M111: 0.08
A112: Taxe patronale d'apprentissage | E112: 0.03 | F112: 0.03 | G112: 0.03 | H112: 0.03 | I112: 0.03 | J112: 0.03 | K112: 0.03 | L112: 0.03 | M112: 0.03
A113: Taxe sur les biens de main morte
A115: Droit de douane
A116: Redevance statistique
...

Sheet Amortissement
A1: Nom | B1: Unité | C1: 2011 | D1: 2012 | E1: 2013 | F1: 2014 | G1: 2015 | H1: 2016 | I1: 2017 | J1: 2018 | K1: 2019 | L1: 2020 | M1: 2021
A3: Durée restante maximum | B3: Années | C3: 11 | D3: 10 | E3: 9 | F3: 8 | G3: 7 | H3: 6 | I3: 5 | J3: 4 | K3: 3 | L3: 2 | M3: 1
A5: I. AMORTISSEMENTS DES CONSTRUCTIONS INDUSTRIELLES
A6: Durée d'amortissement linéaire | B6: Années | C6: 10
A7: Coefficient d'amortissement dégressif | B7: Coefficient | C7: 1
A9: Immobilisations de l'année A1
A10: Durée restante | B10: Années | C10: =IF($C$6<$C$3,$C$6,C$3) -> 10 | D10: =IF(C10=0,0,IF(C10-1<D$3,C10-1,D$3)) -> 9 | E10: =IF(D10=0,0,IF(D10-1<E$3,D10-1,E$3)) -> 8 | F10: =IF(E10=0,0,IF(E10-1<F$3,E10-1,F$3)) -> 7 | G10: =IF(F10=0,0,IF(F10-1<G$3,F10-1,G$3)) -> 6 | H10: =IF(G10=0,0,IF(G10-1<H$3,G10-1,H$3)) -> 5 | I10: =IF(H10=0,0,IF(H10-1<I$3,H10-1,I$3)) -> 4 | J10: =IF(I10=0,0,IF(I10-1<J$3,I10-1,J$3)) -> 3 | K10: =IF(J10=0,0,IF(J10-1<K$3,J10-1,K$3)) -> 2 | ... M10: =IF(L10=0,0,IF(L10-1<M$3,L10-1,M$3)) -> 0
A11: Base amortissable | B11: USD | C11: ='Modèle de base (CM 2003)'!C14 -> 49760265 | D11: =C15 -> 44784238 | E11: =D15 -> 39808212 | F11: =E15 -> 34832186 | G11: =F15 -> 29856159 | H11: =G15 -> 24880132 | I11: =H15 -> 19904106 | J11: =I15 -> 14928080 | K11: =J15 -> 9952053 | ... M11: =L15 -> 0
A12: Inverse de la durée restante | B12: % | C12: =IF(C10=0,0,1/C10) -> 0.1 | D12: =IF(D10=0,0,1/D10) -> 0.11111111 | E12: =IF(E10=0,0,1/E10) -> 0.125 | F12: =IF(F10=0,0,1/F10) -> 0.14285714 | G12: =IF(G10=0,0,1/G10) -> 0.16666667 | H12: =IF(H10=0,0,1/H10) -> 0.2 | I12: =IF(I10=0,0,1/I10) -> 0.25 | J12: =IF(J10=0,0,1/J10) -> 0.33333333 | ... L12: =IF(L10=0,0,1/L10) -> 1
A13: Taux dégressif | B13: % | C13: =IF(C10=0,0,IF($C$7*1/$C$6>C12,$C$7*1/$C$6,C12)) -> 0.1 | D13: =IF(D10=0,0,IF($C$7*1/$C$6>D12,$C$7*1/$C$6,D12)) -> 0.11111111 | E13: =IF(E10=0,0,IF($C$7*1/$C$6>E12,$C$7*1/$C$6,E12)) -> 0.125 | F13: =IF(F10=0,0,IF($C$7*1/$C$6>F12,$C$7*1/$C$6,F12)) -> 0.14285714 | G13: =IF(G10=0,0,IF($C$7*1/$C$6>G12,$C$7*1/$C$6,G12)) -> 0.16666667 | H13: =IF(H10=0,0,IF($C$7*1/$C$6>H12,$C$7*1/$C$6,H12)) -> 0.2 | I13: =IF(I10=0,0,IF($C$7*1/$C$6>I12,$C$7*1/$C$6,I12)) -> 0.25 | J13: =IF(J10=0,0,IF($C$7*1/$C$6>J12,$C$7*1/$C$6,J12)) -> 0.33333333 | ... M13: =IF(M10=0,0,IF($C$7*1/$C$6>M12,$C$7*1/$C$6,M12)) -> 0
A14: Charge d'amortissement | B14: USD | C14: =C11*C13 -> 4976026.5 | D14: =D11*D13 -> 4976026.5 | E14: =E11*E13 -> 4976026.5 | F14: =F11*F13 -> 4976026.5 | G14: =G11*G13 -> 4976026.5 | H14: =H11*H13 -> 4976026.5 | I14: =I11*I13 -> 4976026.5 | J14: =J11*J13 -> 4976026.5 | ... M14: =M11*M13 -> 0
A15: Amortissement restant | B15: USD | C15: =C11-C14 -> 44784238 | D15: =D11-D14 -> 39808212 | E15: =E11-E14 -> 34832186 | F15: =F11-F14 -> 29856159 | G15: =G11-G14 -> 24880132 | H15: =H11-H14 -> 19904106 | I15: =I11-I14 -> 14928080 | J15: =J11-J14 -> 9952053 | ... M15: =M11-M14 -> 0
A17: Immobilisations de l'année A2
A18: Durée restante | B18: Années | D18: =IF($C$6<D$3,$C$6,D$3) -> 10 | E18: =IF(D18=0,0,IF(D18-1<E$3,D18-1,E$3)) -> 9 | F18: =IF(E18=0,0,IF(E18-1<F$3,E18-1,F$3)) -> 8 | G18: =IF(F18=0,0,IF(F18-1<G$3,F18-1,G$3)) -> 7 | H18: =IF(G18=0,0,IF(G18-1<H$3,G18-1,H$3)) -> 6 | I18: =IF(H18=0,0,IF(H18-1<I$3,H18-1,I$3)) -> 5 | J18: =IF(I18=0,0,IF(I18-1<J$3,I18-1,J$3)) -> 4 | K18: =IF(J18=0,0,IF(J18-1<K$3,J18-1,K$3)) -> 3 | L18: =IF(K18=0,0,IF(K18-1<L$3,K18-1,L$3)) -> 2 | M18: =IF(L18=0,0,IF(L18-1<M$3,L18-1,M$3)) -> 1
A19: Base amortissable | B19: USD | D19: ='Modèle de base (CM 2003)'!D14 -> 116107284 | E19: =D23 -> 1.0449656e+08 | F19: =E23 -> 92885827 | G19: =F23 -> 81275099 | H19: =G23 -> 69664370 | I19: =H23 -> 58053642 | J19: =I23 -> 46442914 | K19: =J23 -> 34832185 | L19: =K23 -> 23221457 | M19: =L23 -> 11610728
A20: Inverse de la durée restante | B20: % | D20: =IF(D18=0,0,1/D18) -> 0.1 | E20: =IF(E18=0,0,1/E18) -> 0.11111111 | F20: =IF(F18=0,0,1/F18) -> 0.125 | G20: =IF(G18=0,0,1/G18) -> 0.14285714 | H20: =IF(H18=0,0,1/H18) -> 0.16666667 | I20: =IF(I18=0,0,1/I18) -> 0.2 | J20: =IF(J18=0,0,1/J18) -> 0.25 | K20: =IF(K18=0,0,1/K18) -> 0.33333333 | ... M20: =IF(M18=0,0,1/M18) -> 1
A21: Taux dégressif | B21: % | D21: =IF(D18=0,0,IF($C$7*1/$C$6>D20,$C$7*1/$C$6,D20)) -> 0.1 | E21: =IF(E18=0,0,IF($C$7*1/$C$6>E20,$C$7*1/$C$6,E20)) -> 0.11111111 | F21: =IF(F18=0,0,IF($C$7*1/$C$6>F20,$C$7*1/$C$6,F20)) -> 0.125 | G21: =IF(G18=0,0,IF($C$7*1/$C$6>G20,$C$7*1/$C$6,G20)) -> 0.14285714 | H21: =IF(H18=0,0,IF($C$7*1/$C$6>H20,$C$7*1/$C$6,H20)) -> 0.16666667 | I21: =IF(I18=0,0,IF($C$7*1/$C$6>I20,$C$7*1/$C$6,I20)) -> 0.2 | J21: =IF(J18=0,0,IF($C$7*1/$C$6>J20,$C$7*1/$C$6,J20)) -> 0.25 | K21: =IF(K18=0,0,IF($C$7*1/$C$6>K20,$C$7*1/$C$6,K20)) -> 0.33333333 | ... M21: =IF(M18=0,0,IF($C$7*1/$C$6>M20,$C$7*1/$C$6,M20)) -> 1
A22: Charge d'amortissement | B22: USD | D22: =D19*D21 -> 11610728 | E22: =E19*E21 -> 11610728 | F22: =F19*F21 -> 11610728 | G22: =G19*G21 -> 11610728 | H22: =H19*H21 -> 11610728 | I22: =I19*I21 -> 11610728 | J22: =J19*J21 -> 11610728 | K22: =K19*K21 -> 11610728 | ... M22: =M19*M21 -> 11610728
A23: Amortissement restant | B23: USD | D23: =D19-D22 -> 1.0449656e+08 | E23: =E19-E22 -> 92885827 | F23: =F19-F22 -> 81275099 | G23: =G19-G22 -> 69664370 | H23: =H19-H22 -> 58053642 | I23: =I19-I22 -> 46442914 | J23: =J19-J22 -> 34832185 | K23: =K19-K22 -> 23221457 | ... M23: =M19-M22 -> 0
A25: Amortissements des constructions industrielles | B25: USD | C25: =C$14+C$22 -> 4976026.5 | D25: =D$14+D$22 -> 16586755 | E25: =E$14+E$22 -> 16586755 | F25: =F$14+F$22 -> 16586755 | G25: =G$14+G$22 -> 16586755 | H25: =H$14+H$22 -> 16586755 | I25: =I$14+I$22 -> 16586755 | J25: =J$14+J$22 -> 16586755 | ... M25: =M$14+M$22 -> 11610728
A27: II. AMORTISSEMENTS DES BIENS D'EQUIPEMENT
A28: Durée d'amortissement linéaire | B28: Années | C28: 5
A29: Coefficient d'amortissement dégressif | B29: Coefficient | C29: 2
A31: Immobilisations de l'année A1
A32: Durée restante | B32: Années | C32: =IF($C$28<C$3,$C$28,C$3) -> 5 | D32: =IF(C32=0,0,IF(C32-1<D$3,C32-1,D$3)) -> 4 | E32: =IF(D32=0,0,IF(D32-1<E$3,D32-1,E$3)) -> 3 | F32: =IF(E32=0,0,IF(E32-1<F$3,E32-1,F$3)) -> 2 | G32: =IF(F32=0,0,IF(F32-1<G$3,F32-1,G$3)) -> 1 | H32: =IF(G32=0,0,IF(G32-1<H$3,G32-1,H$3)) -> 0 | I32: =IF(H32=0,0,IF(H32-1<I$3,H32-1,I$3)) -> 0 | J32: =IF(I32=0,0,IF(I32-1<J$3,I32-1,J$3)) -> 0 | K32: =IF(J32=0,0,IF(J32-1<K$3,J32-1,K$3)) -> 0 | ... M32: =IF(L32=0,0,IF(L32-1<M$3,L32-1,M$3)) -> 0
A33: Base amortissable | B33: USD | C33: ='Modèle de base (CM 2003)'!C15 -> 23685527 | D33: =C37 -> 14211316 | E33: =D37 -> 8526789.7 | F33: =E37 -> 5116073.8 | G33: =F37 -> 2558036.9 | H33: =G37 -> 0 | I33: =H37 -> 0 | J33: =I37 -> 0 | K33: =J37 -> 0 | ... M33: =L37 -> 0
A34: Inverse de la durée restante | B34: % | C34: =IF(C32=0,0,1/C32) -> 0.2 | D34: =IF(D32=0,0,1/D32) -> 0.25 | E34: =IF(E32=0,0,1/E32) -> 0.33333333 | F34: =IF(F32=0,0,1/F32) -> 0.5 | G34: =IF(G32=0,0,1/G32) -> 1 | H34: =IF(H32=0,0,1/H32) -> 0 | I34: =IF(I32=0,0,1/I32) -> 0 | J34: =IF(J32=0,0,1/J32) -> 0 | ... M34: =IF(M32=0,0,1/M32) -> 0
A35: Taux dégressif | B35: % | C35: =IF(C32=0,0,IF($C$29*1/$C$28>C34,$C$29*1/$C$28,C34)) -> 0.4 | D35: =IF(D32=0,0,IF($C$29*1/$C$28>D34,$C$29*1/$C$28,D34)) -> 0.4 | E35: =IF(E32=0,0,IF($C$29*1/$C$28>E34,$C$29*1/$C$28,E34)) -> 0.4 | F35: =IF(F32=0,0,IF($C$29*1/$C$28>F34,$C$29*1/$C$28,F34)) -> 0.5 | G35: =IF(G32=0,0,IF($C$29*1/$C$28>G34,$C$29*1/$C$28,G34)) -> 1 | H35: =IF(H32=0,0,IF($C$29*1/$C$28>H34,$C$29*1/$C$28,H34)) -> 0 | I35: =IF(I32=0,0,IF($C$29*1/$C$28>I34,$C$29*1/$C$28,I34)) -> 0 | J35: =IF(J32=0,0,IF($C$29*1/$C$28>J34,$C$29*1/$C$28,J34)) -> 0 | ... M35: =IF(M32=0,0,IF($C$29*1/$C$28>M34,$C$29*1/$C$28,M34)) -> 0
A36: Charge d'amortissement | B36: USD | C36: =C33*C35 -> 9474210.8 | D36: =D33*D35 -> 5684526.5 | E36: =E33*E35 -> 3410715.9 | F36: =F33*F35 -> 2558036.9 | G36: =G33*G35 -> 2558036.9 | H36: =H33*H35 -> 0 | I36: =I33*I35 -> 0 | J36: =J33*J35 -> 0 | ... M36: =M33*M35 -> 0
A37: Amortissement restant | B37: USD | C37: =C33-C36 -> 14211316 | D37: =D33-D36 -> 8526789.7 | E37: =E33-E36 -> 5116073.8 | F37: =F33-F36 -> 2558036.9 | G37: =G33-G36 -> 0 | H37: =H33-H36 -> 0 | I37: =I33-I36 -> 0 | J37: =J33-J36 -> 0 | ... M37: =M33-M36 -> 0
A39: Immobilisations de l'année A2
A40: Durée restante | B40: Années | D40: =IF($C$28<D$3,$C$28,D$3) -> 5 | E40: =IF(D40=0,0,IF(D40-1<E$3,D40-1,E$3)) -> 4 | F40: =IF(E40=0,0,IF(E40-1<F$3,E40-1,F$3)) -> 3 | G40: =IF(F40=0,0,IF(F40-1<G$3,F40-1,G$3)) -> 2 | H40: =IF(G40=0,0,IF(G40-1<H$3,G40-1,H$3)) -> 1 | I40: =IF(H40=0,0,IF(H40-1<I$3,H40-1,I$3)) -> 0 | J40: =IF(I40=0,0,IF(I40-1<J$3,I40-1,J$3)) -> 0 | K40: =IF(J40=0,0,IF(J40-1<K$3,J40-1,K$3)) -> 0 | L40: =IF(K40=0,0,IF(K40-1<L$3,K40-1,L$3)) -> 0 | M40: =IF(L40=0,0,IF(L40-1<M$3,L40-1,M$3)) -> 0
A41: Base amortissable | B41: USD | D41: ='Modèle de base (CM 2003)'!D15 -> 125300533 | E41: =D45 -> 75180320 | F41: =E45 -> 45108192 | G41: =F45 -> 27064915 | H41: =G45 -> 13532458 | I41: =H45 -> 0 | J41: =I45 -> 0 | K41: =J45 -> 0 | L41: =K45 -> 0 | M41: =L45 -> 0
A42: Inverse de la durée restante | B42: % | D42: =IF(D40=0,0,1/D40) -> 0.2 | E42: =IF(E40=0,0,1/E40) -> 0.25 | F42: =IF(F40=0,0,1/F40) -> 0.33333333 | G42: =IF(G40=0,0,1/G40) -> 0.5 | H42: =IF(H40=0,0,1/H40) -> 1 | I42: =IF(I40=0,0,1/I40) -> 0 | J42: =IF(J40=0,0,1/J40) -> 0 | K42: =IF(K40=0,0,1/K40) -> 0 | ... M42: =IF(M40=0,0,1/M40) -> 0
A43: Taux dégressif | B43: % | D43: =IF(D40=0,0,IF($C$29*1/$C$28>D42,$C$29*1/$C$28,D42)) -> 0.4 | E43: =IF(E40=0,0,IF($C$29*1/$C$28>E42,$C$29*1/$C$28,E42)) -> 0.4 | F43: =IF(F40=0,0,IF($C$29*1/$C$28>F42,$C$29*1/$C$28,F42)) -> 0.4 | G43: =IF(G40=0,0,IF($C$29*1/$C$28>G42,$C$29*1/$C$28,G42)) -> 0.5 | H43: =IF(H40=0,0,IF($C$29*1/$C$28>H42,$C$29*1/$C$28,H42)) -> 1 | I43: =IF(I40=0,0,IF($C$29*1/$C$28>I42,$C$29*1/$C$28,I42)) -> 0 | J43: =IF(J40=0,0,IF($C$29*1/$C$28>J42,$C$29*1/$C$28,J42)) -> 0 | K43: =IF(K40=0,0,IF($C$29*1/$C$28>K42,$C$29*1/$C$28,K42)) -> 0 | ... M43: =IF(M40=0,0,IF($C$29*1/$C$28>M42,$C$29*1/$C$28,M42)) -> 0
A44: Charge d'amortissement | B44: USD | D44: =D41*D43 -> 50120213 | E44: =E41*E43 -> 30072128 | F44: =F41*F43 -> 18043277 | G44: =G41*G43 -> 13532458 | H44: =H41*H43 -> 13532458 | I44: =I41*I43 -> 0 | J44: =J41*J43 -> 0 | K44: =K41*K43 -> 0 | ... M44: =M41*M43 -> 0
A45: Amortissement restant | B45: USD | D45: =D41-D44 -> 75180320 | E45: =E41-E44 -> 45108192 | F45: =F41-F44 -> 27064915 | G45: =G41-G44 -> 13532458 | H45: =H41-H44 -> 0 | I45: =I41-I44 -> 0 | J45: =J41-J44 -> 0 | K45: =K41-K44 -> 0 | ... M45: =M41-M44 -> 0
A47: Immobilisations de l'année A3
A48: Durée restante | B48: Années | E48: =IF($C$28<E$3,$C$28,E$3) -> 5 | F48: =IF(E48=0,0,IF(E48-1<F$3,E48-1,F$3)) -> 4 | G48: =IF(F48=0,0,IF(F48-1<G$3,F48-1,G$3)) -> 3 | H48: =IF(G48=0,0,IF(G48-1<H$3,G48-1,H$3)) -> 2 | I48: =IF(H48=0,0,IF(H48-1<I$3,H48-1,I$3)) -> 1 | J48: =IF(I48=0,0,IF(I48-1<J$3,I48-1,J$3)) -> 0 | K48: =IF(J48=0,0,IF(J48-1<K$3,J48-1,K$3)) -> 0 | L48: =IF(K48=0,0,IF(K48-1<L$3,K48-1,L$3)) -> 0 | M48: =IF(L48=0,0,IF(L48-1<M$3,L48-1,M$3)) -> 0
A49: Base amortissable | B49: USD | E49: ='Modèle de base (CM 2003)'!E15 -> 11632917 | F49: =E53 -> 6979750.2 | G49: =F53 -> 4187850.1 | H49: =G53 -> 2512710.1 | I49: =H53 -> 1256355 | J49: =I53 -> 0 | K49: =J53 -> 0 | L49: =K53 -> 0 | M49: =L53 -> 0
A50: Inverse de la durée restante | B50: % | E50: =IF(E48=0,0,1/E48) -> 0.2 | F50: =IF(F48=0,0,1/F48) -> 0.25 | G50: =IF(G48=0,0,1/G48) -> 0.33333333 | H50: =IF(H48=0,0,1/H48) -> 0.5 | I50: =IF(I48=0,0,1/I48) -> 1 | J50: =IF(J48=0,0,1/J48) -> 0 | K50: =IF(K48=0,0,1/K48) -> 0 | L50: =IF(L48=0,0,1/L48) -> 0 | M50: =IF(M48=0,0,1/M48) -> 0
A51: Taux dégressif | B51: % | E51: =IF(E48=0,0,IF($C$29*1/$C$28>E50,$C$29*1/$C$28,E50)) -> 0.4 | F51: =IF(F48=0,0,IF($C$29*1/$C$28>F50,$C$29*1/$C$28,F50)) -> 0.4 | G51: =IF(G48=0,0,IF($C$29*1/$C$28>G50,$C$29*1/$C$28,G50)) -> 0.4 | H51: =IF(H48=0,0,IF($C$29*1/$C$28>H50,$C$29*1/$C$28,H50)) -> 0.5 | I51: =IF(I48=0,0,IF($C$29*1/$C$28>I50,$C$29*1/$C$28,I50)) -> 1 | J51: =IF(J48=0,0,IF($C$29*1/$C$28>J50,$C$29*1/$C$28,J50)) -> 0 | K51: =IF(K48=0,0,IF($C$29*1/$C$28>K50,$C$29*1/$C$28,K50)) -> 0 | L51: =IF(L48=0,0,IF($C$29*1/$C$28>L50,$C$29*1/$C$28,L50)) -> 0 | M51: =IF(M48=0,0,IF($C$29*1/$C$28>M50,$C$29*1/$C$28,M50)) -> 0
A52: Charge d'amortissement | B52: USD | E52: =E49*E51 -> 4653166.8 | F52: =F49*F51 -> 2791900.1 | G52: =G49*G51 -> 1675140 | H52: =H49*H51 -> 1256355 | I52: =I49*I51 -> 1256355 | J52: =J49*J51 -> 0 | K52: =K49*K51 -> 0 | L52: =L49*L51 -> 0 | M52: =M49*M51 -> 0
A53: Amortissement restant | B53: USD | E53: =E49-E52 -> 6979750.2 | F53: =F49-F52 -> 4187850.1 | G53: =G49-G52 -> 2512710.1 | H53: =H49-H52 -> 1256355 | I53: =I49-I52 -> 0 | J53: =J49-J52 -> 0 | K53: =K49-K52 -> 0 | L53: =L49-L52 -> 0 | M53: =M49-M52 -> 0
A55: Immobilisations de l'année A4
A56: Durée restante | B56: Années | F56: =IF($C$28<F$3,$C$28,F$3) -> 5 | G56: =IF(F56=0,0,IF(F56-1<G$3,F56-1,G$3)) -> 4 | H56: =IF(G56=0,0,IF(G56-1<H$3,G56-1,H$3)) -> 3 | I56: =IF(H56=0,0,IF(H56-1<I$3,H56-1,I$3)) -> 2 | J56: =IF(I56=0,0,IF(I56-1<J$3,I56-1,J$3)) -> 1 | K56: =IF(J56=0,0,IF(J56-1<K$3,J56-1,K$3)) -> 0 | L56: =IF(K56=0,0,IF(K56-1<L$3,K56-1,L$3)) -> 0 | M56: =IF(L56=0,0,IF(L56-1<M$3,L56-1,M$3)) -> 0
A57: Base amortissable | B57: USD | F57: ='Modèle de base (CM 2003)'!F15 -> 3722927 | G57: =F61 -> 2233756.2 | H57: =G61 -> 1340253.7 | I57: =H61 -> 804152.23 | J57: =I61 -> 402076.12 | K57: =J61 -> 0 | L57: =K61 -> 0 | M57: =L61 -> 0
A58: Inverse de la durée restante | B58: % | F58: =IF(F56=0,0,1/F56) -> 0.2 | G58: =IF(G56=0,0,1/G56) -> 0.25 | H58: =IF(H56=0,0,1/H56) -> 0.33333333 | I58: =IF(I56=0,0,1/I56) -> 0.5 | J58: =IF(J56=0,0,1/J56) -> 1 | K58: =IF(K56=0,0,1/K56) -> 0 | L58: =IF(L56=0,0,1/L56) -> 0 | M58: =IF(M56=0,0,1/M56) -> 0
A59: Taux dégressif | B59: % | F59: =IF(F56=0,0,IF($C$29*1/$C$28>F58,$C$29*1/$C$28,F58)) -> 0.4 | G59: =IF(G56=0,0,IF($C$29*1/$C$28>G58,$C$29*1/$C$28,G58)) -> 0.4 | H59: =IF(H56=0,0,IF($C$29*1/$C$28>H58,$C$29*1/$C$28,H58)) -> 0.4 | I59: =IF(I56=0,0,IF($C$29*1/$C$28>I58,$C$29*1/$C$28,I58)) -> 0.5 | J59: =IF(J56=0,0,IF($C$29*1/$C$28>J58,$C$29*1/$C$28,J58)) -> 1 | K59: =IF(K56=0,0,IF($C$29*1/$C$28>K58,$C$29*1/$C$28,K58)) -> 0 | L59: =IF(L56=0,0,IF($C$29*1/$C$28>L58,$C$29*1/$C$28,L58)) -> 0 | M59: =IF(M56=0,0,IF($C$29*1/$C$28>M58,$C$29*1/$C$28,M58)) -> 0
A60: Charge d'amortissement | B60: USD | F60: =F57*F59 -> 1489170.8 | G60: =G57*G59 -> 893502.48 | H60: =H57*H59 -> 536101.49 | I60: =I57*I59 -> 402076.12 | J60: =J57*J59 -> 402076.12 | K60: =K57*K59 -> 0 | L60: =L57*L59 -> 0 | M60: =M57*M59 -> 0
A61: Amortissement restant | B61: USD | F61: =F57-F60 -> 2233756.2 | G61: =G57-G60 -> 1340253.7 | H61: =H57-H60 -> 804152.23 | I61: =I57-I60 -> 402076.12 | J61: =J57-J60 -> 0 | K61: =K57-K60 -> 0 | L61: =L57-L60 -> 0 | M61: =M57-M60 -> 0
A63: Immobilisations de l'année A5
A64: Durée restante | B64: Années | G64: =IF($C$28<G$3,$C$28,G$3) -> 5 | H64: =IF(G64=0,0,IF(G64-1<H$3,G64-1,H$3)) -> 4 | I64: =IF(H64=0,0,IF(H64-1<I$3,H64-1,I$3)) -> 3 | J64: =IF(I64=0,0,IF(I64-1<J$3,I64-1,J$3)) -> 2 | K64: =IF(J64=0,0,IF(J64-1<K$3,J64-1,K$3)) -> 1 | L64: =IF(K64=0,0,IF(K64-1<L$3,K64-1,L$3)) -> 0 | M64: =IF(L64=0,0,IF(L64-1<M$3,L64-1,M$3)) -> 0
A65: Base amortissable | B65: USD | G65: ='Modèle de base (CM 2003)'!G15 -> 18272647 | H65: =G69 -> 10963588 | I65: =H69 -> 6578152.9 | J65: =I69 -> 3946891.8 | K65: =J69 -> 1973445.9 | L65: =K69 -> 0 | M65: =L69 -> 0
A66: Inverse de la durée restante | B66: % | G66: =IF(G64=0,0,1/G64) -> 0.2 | H66: =IF(H64=0,0,1/H64) -> 0.25 | I66: =IF(I64=0,0,1/I64) -> 0.33333333 | J66: =IF(J64=0,0,1/J64) -> 0.5 | K66: =IF(K64=0,0,1/K64) -> 1 | L66: =IF(L64=0,0,1/L64) -> 0 | M66: =IF(M64=0,0,1/M64) -> 0
A67: Taux dégressif | B67: % | G67: =IF(G64=0,0,IF($C$29*1/$C$28>G66,$C$29*1/$C$28,G66)) -> 0.4 | H67: =IF(H64=0,0,IF($C$29*1/$C$28>H66,$C$29*1/$C$28,H66)) -> 0.4 | I67: =IF(I64=0,0,IF($C$29*1/$C$28>I66,$C$29*1/$C$28,I66)) -> 0.4 | J67: =IF(J64=0,0,IF($C$29*1/$C$28>J66,$C$29*1/$C$28,J66)) -> 0.5 | K67: =IF(K64=0,0,IF($C$29*1/$C$28>K66,$C$29*1/$C$28,K66)) -> 1 | L67: =IF(L64=0,0,IF($C$29*1/$C$28>L66,$C$29*1/$C$28,L66)) -> 0 | M67: =IF(M64=0,0,IF($C$29*1/$C$28>M66,$C$29*1/$C$28,M66)) -> 0
A68: Charge d'amortissement | B68: USD | G68: =G65*G67 -> 7309058.8 | H68: =H65*H67 -> 4385435.3 | I68: =I65*I67 -> 2631261.2 | J68: =J65*J67 -> 1973445.9 | K68: =K65*K67 -> 1973445.9 | L68: =L65*L67 -> 0 | M68: =M65*M67 -> 0
A69: Amortissement restant | B69: USD | G69: =G65-G68 -> 10963588 | H69: =H65-H68 -> 6578152.9 | I69: =I65-I68 -> 3946891.8 | J69: =J65-J68 -> 1973445.9 | K69: =K65-K68 -> 0 | L69: =L65-L68 -> 0 | M69: =M65-M68 -> 0
A71: Immobilisations de l'année A6
A72: Durée restante | B72: Années | H72: =IF($C$28<H$3,$C$28,H$3) -> 5 | I72: =IF(H72=0,0,IF(H72-1<I$3,H72-1,I$3)) -> 4 | J72: =IF(I72=0,0,IF(I72-1<J$3,I72-1,J$3)) -> 3 | K72: =IF(J72=0,0,IF(J72-1<K$3,J72-1,K$3)) -> 2 | L72: =IF(K72=0,0,IF(K72-1<L$3,K72-1,L$3)) -> 1 | M72: =IF(L72=0,0,IF(L72-1<M$3,L72-1,M$3)) -> 0
A73: Base amortissable | B73: USD | H73: ='Modèle de base (CM 2003)'!H15 -> 4482500 | I73: =H77 -> 2689500 | J73: =I77 -> 1613700 | K73: =J77 -> 968220 | L73: =K77 -> 484110 | M73: =L77 -> 0
A74: Inverse de la durée restante | B74: % | H74: =IF(H72=0,0,1/H72) -> 0.2 | I74: =IF(I72=0,0,1/I72) -> 0.25 | J74: =IF(J72=0,0,1/J72) -> 0.33333333 | K74: =IF(K72=0,0,1/K72) -> 0.5 | L74: =IF(L72=0,0,1/L72) -> 1 | M74: =IF(M72=0,0,1/M72) -> 0
A75: Taux dégressif | B75: % | H75: =IF(H72=0,0,IF($C$29*1/$C$28>H74,$C$29*1/$C$28,H74)) -> 0.4 | I75: =IF(I72=0,0,IF($C$29*1/$C$28>I74,$C$29*1/$C$28,I74)) -> 0.4 | J75: =IF(J72=0,0,IF($C$29*1/$C$28>J74,$C$29*1/$C$28,J74)) -> 0.4 | K75: =IF(K72=0,0,IF($C$29*1/$C$28>K74,$C$29*1/$C$28,K74)) -> 0.5 | L75: =IF(L72=0,0,IF($C$29*1/$C$28>L74,$C$29*1/$C$28,L74)) -> 1 | M75: =IF(M72=0,0,IF($C$29*1/$C$28>M74,$C$29*1/$C$28,M74)) -> 0
A76: Charge d'amortissement | B76: USD | H76: =H73*H75 -> 1793000 | I76: =I73*I75 -> 1075800 | J76: =J73*J75 -> 645480 | K76: =K73*K75 -> 484110 | L76: =L73*L75 -> 484110 | M76: =M73*M75 -> 0
A77: Amortissement restant | B77: USD | H77: =H73-H76 -> 2689500 | I77: =I73-I76 -> 1613700 | J77: =J73-J76 -> 968220 | K77: =K73-K76 -> 484110 | L77: =L73-L76 -> 0 | M77: =M73-M76 -> 0
A79: Immobilisations de l'année A7
A80: Durée restante | B80: Années | I80: =IF($C$28<I$3,$C$28,I$3) -> 5 | J80: =IF(I80=0,0,IF(I80-1<J$3,I80-1,J$3)) -> 4 | K80: =IF(J80=0,0,IF(J80-1<K$3,J80-1,K$3)) -> 3 | L80: =IF(K80=0,0,IF(K80-1<L$3,K80-1,L$3)) -> 2 | M80: =IF(L80=0,0,IF(L80-1<M$3,L80-1,M$3)) -> 1
A81: Base amortissable | B81: USD | I81: ='Modèle de base (CM 2003)'!I15 -> 2137128 | J81: =I85 -> 1282276.8 | K81: =J85 -> 769366.08 | L81: =K85 -> 461619.65 | M81: =L85 -> 230809.82
A82: Inverse de la durée restante | B82: % | I82: =IF(I80=0,0,1/I80) -> 0.2 | J82: =IF(J80=0,0,1/J80) -> 0.25 | K82: =IF(K80=0,0,1/K80) -> 0.33333333 | L82: =IF(L80=0,0,1/L80) -> 0.5 | M82: =IF(M80=0,0,1/M80) -> 1
A83: Taux dégressif | B83: % | I83: =IF(I80=0,0,IF($C$29*1/$C$28>I82,$C$29*1/$C$28,I82)) -> 0.4 | J83: =IF(J80=0,0,IF($C$29*1/$C$28>J82,$C$29*1/$C$28,J82)) -> 0.4 | K83: =IF(K80=0,0,IF($C$29*1/$C$28>K82,$C$29*1/$C$28,K82)) -> 0.4 | L83: =IF(L80=0,0,IF($C$29*1/$C$28>L82,$C$29*1/$C$28,L82)) -> 0.5 | M83: =IF(M80=0,0,IF($C$29*1/$C$28>M82,$C$29*1/$C$28,M82)) -> 1
A84: Charge d'amortissement | B84: USD | I84: =I81*I83 -> 854851.2 | J84: =J81*J83 -> 512910.72 | K84: =K81*K83 -> 307746.43 | L84: =L81*L83 -> 230809.82 | M84: =M81*M83 -> 230809.82
A85: Amortissement restant | B85: USD | I85: =I81-I84 -> 1282276.8 | J85: =J81-J84 -> 769366.08 | K85: =K81-K84 -> 461619.65 | L85: =L81-L84 -> 230809.82 | M85: =M81-M84 -> 0
A87: Immobilisations de l'année A8
A88: Durée restante | B88: Années | J88: =IF($C$28<J$3,$C$28,J$3) -> 4 | K88: =IF(J88=0,0,IF(J88-1<K$3,J88-1,K$3)) -> 3 | L88: =IF(K88=0,0,IF(K88-1<L$3,K88-1,L$3)) -> 2 | M88: =IF(L88=0,0,IF(L88-1<M$3,L88-1,M$3)) -> 1
A89: Base amortissable | B89: USD | J89: ='Modèle de base (CM 2003)'!J15 -> 1103055 | K89: =J93 -> 661833 | L89: =K93 -> 397099.8 | M89: =L93 -> 198549.9
A90: Inverse de la durée restante | B90: % | J90: =IF(J88=0,0,1/J88) -> 0.25 | K90: =IF(K88=0,0,1/K88) -> 0.33333333 | L90: =IF(L88=0,0,1/L88) -> 0.5 | M90: =IF(M88=0,0,1/M88) -> 1
A91: Taux dégressif | B91: % | J91: =IF(J88=0,0,IF($C$29*1/$C$28>J90,$C$29*1/$C$28,J90)) -> 0.4 | K91: =IF(K88=0,0,IF($C$29*1/$C$28>K90,$C$29*1/$C$28,K90)) -> 0.4 | L91: =IF(L88=0,0,IF($C$29*1/$C$28>L90,$C$29*1/$C$28,L90)) -> 0.5 | M91: =IF(M88=0,0,IF($C$29*1/$C$28>M90,$C$29*1/$C$28,M90)) -> 1
A92: Charge d'amortissement | B92: USD | J92: =J89*J91 -> 441222 | K92: =K89*K91 -> 264733.2 | L92: =L89*L91 -> 198549.9 | M92: =M89*M91 -> 198549.9
A93: Amortissement restant | B93: USD | J93: =J89-J92 -> 661833 | K93: =K89-K92 -> 397099.8 | L93: =L89-L92 -> 198549.9 | M93: =M89-M92 -> 0
A95: Immobilisations de l'année A9
A96: Durée restante | B96: Années | K96: =IF($C$28<K$3,$C$28,K$3) -> 3 | L96: =IF(K96=0,0,IF(K96-1<L$3,K96-1,L$3)) -> 2 | M96: =IF(L96=0,0,IF(L96-1<M$3,L96-1,M$3)) -> 1
A97: Base amortissable | B97: USD | K97: ='Modèle de base (CM 2003)'!K15 -> 4934651 | L97: =K101 -> 2960790.6 | M97: =L101 -> 1480395.3
A98: Inverse de la durée restante | B98: % | K98: =IF(K96=0,0,1/K96) -> 0.33333333 | L98: =IF(L96=0,0,1/L96) -> 0.5 | M98: =IF(M96=0,0,1/M96) -> 1
A99: Taux dégressif | B99: % | K99: =IF(K96=0,0,IF($C$29*1/$C$28>K98,$C$29*1/$C$28,K98)) -> 0.4 | L99: =IF(L96=0,0,IF($C$29*1/$C$28>L98,$C$29*1/$C$28,L98)) -> 0.5 | M99: =IF(M96=0,0,IF($C$29*1/$C$28>M98,$C$29*1/$C$28,M98)) -> 1
A100: Charge d'amortissement | B100: USD | K100: =K97*K99 -> 1973860.4 | L100: =L97*L99 -> 1480395.3 | M100: =M97*M99 -> 1480395.3
A101: Amortissement restant | B101: USD | K101: =K97-K100 -> 2960790.6 | L101: =L97-L100 -> 1480395.3 | M101: =M97-M100 -> 0
A103: Immobilisations de l'année A10
A104: Durée restante | B104: Années | L104: =IF($C$28<L$3,$C$28,L$3) -> 2 | M104: =IF(L104=0,0,IF(L104-1<M$3,L104-1,M$3)) -> 1
A105: Base amortissable | B105: USD | L105: ='Modèle de base (CM 2003)'!L15 -> 2727670 | M105: =L109 -> 1363835
A106: Inverse de la durée restante | B106: % | L106: =IF(L104=0,0,1/L104) -> 0.5 | M106: =IF(M104=0,0,1/M104) -> 1
A107: Taux dégressif | B107: % | L107: =IF(L104=0,0,IF($C$29*1/$C$28>L106,$C$29*1/$C$28,L106)) -> 0.5 | M107: =IF(M104=0,0,IF($C$29*1/$C$28>M106,$C$29*1/$C$28,M106)) -> 1
A108: Charge d'amortissement | B108: USD | L108: =L105*L107 -> 1363835 | M108: =M105*M107 -> 1363835
A109: Amortissement restant | B109: USD | L109: =L105-L108 -> 1363835 | M109: =M105-M108 -> 0
A111: Immobilisations de l'année A11
A112: Durée restante | B112: Années | M112: =IF($C$28<M$3,$C$28,M$3) -> 1
A113: Base amortissable | B113: USD | M113: ='Modèle de base (CM 2003)'!M15 -> 542926
A114: Inverse de la durée restante | B114: % | M114: =IF(M112=0,0,1/M112) -> 1
A115: Taux dégressif | B115: % | M115: =IF(M112=0,0,IF($C$29*1/$C$28>M114,$C$29*1/$C$28,M114)) -> 1
A116: Charge d'amortissement | B116: USD | M116: =M113*M115 -> 542926
A117: Amortissement restant | B117: USD | M117: =M113-M116 -> 0
...

Sheet Données de la mine
A1: Projet aurifère_De Houndé | B1: Unités | C1: 2011 | D1: 2012 | E1: 2013 | F1: 2014 | G1: 2015 | H1: 2016 | I1: 2017 | J1: 2018 | K1: 2019 | L1: 2020 | M1: 2021
A4: Production
A5: Quantité Traité | B5: t
A6: Teneur en or | B6: g/t
A7: Quantité d'Or Récupéré | B7: oz | E7: 191176 | F7: 215238 | G7: 189807 | H7: 168325 | I7: 210971 | J7: 167700 | K7: 136799 | L7: 152798 | M7: 119370
A8: Cours de l'or | B8: 1600 | E8: 1300 | F8: 1300 | G8: 1300 | H8: 1300 | I8: 1300 | J8: 1300 | K8: 1300 | L8: 1300 | M8: 1300
A9: Chiffre d'Affaire | B9: $ | E9: 305881600 | F9: 344380800 | G9: 303691200 | H9: 269320000 | I9: 337553600 | J9: 268320000 | K9: 218878400 | L9: 244476800 | M9: 190992000
A10: Taux de change | B10: 493.00615
A11: Taux d'actualisation | B11: 0.05
A13: Coûts d'investissement (CAPEX)
A14: Coûts des construction industrielles | B14: $ | C14: 49760265 | D14: 116107284
A15: Coûts des biens d'équipement | C15: 23685527 | D15: 125300533 | E15: 11632917 | F15: 3722927 | G15: 18272647 | H15: 4482500 | I15: 2137128 | J15: 1103055 | K15: 4934651 | L15: 2727670 | M15: 542926
A16: Autres depenses | B16: $ | C16: 0 | D16: 0 | E16: 1595000 | F16: 2708200 | G16: 249700 | H16: 2581553 | I16: 469553 | J16: 3654542 | K16: 249700 | L16: 106700 | M16: 0
A17: Coûts de réhabilitation du site | B17: $ | E17: 2830244 | F17: 3314368 | G17: 3215137 | H17: 3842412 | I17: 4018506 | J17: 2935298 | K17: 1813443 | L17: 1249254 | M17: 3165512
A18: TOTAL CAPITAL | B18: $ | C18: 73445792 | D18: 241407817 | E18: 16058161 | F18: 9745495 | G18: 21737484 | H18: 10906465 | I18: 6625187 | J18: 7692895 | K18: 6997794 | L18: 4083624 | M18: 3708438
A20: Coûts d'exploitation (Opex)/hors redevance | B20: $ | C20: 0 | D20: 0 | E20: 115668594 | F20: 128519703 | G20: 131246978 | H20: 152348402 | I20: 157632470 | J20: 132358509 | K20: 107272479 | L20: 96975692 | M20: 9542514
A21: Coûts d'exploitation moyen (Opex) /hors redevance | B21: $/oz | E21: 605.03721 | F21: 597.10508 | G21: 691.47596 | H21: 905.08482 | I21: 747.17601 | J21: 789.25766 | K21: 784.16128 | L21: 634.66598 | M21: 79.940638
